Workbook

Sheet Candidates
A1: Phase 0 candidates
A2: You can edit the six score columns (1–3), Pursue? and Notes (light blue). Total, Band, and the Summary sheet recalculate. Example: Pursue? = maybe, Notes = "talk to 2 bookkeepers before deciding". Grey columns are the scout's original output for comparison.
A3: Colors: higher is better. Green = good (score 3, Total 15+, Shortlist). Yellow = neutral (score 2, Total 10–14). Red = weak (score 1, Total under 10, Drop).
A4: # | B4: Source | C4: Problem | D4: Link | E4: Freq | F4: Pain | G4: Messy | H4: Backend | I4: Reach | J4: Free data | K4: Total | L4: Band | M4: Pursue? | N4: Notes | O4: Scores changed | P4: Scout total | Q4: Rules-only total | R4: Rules-only rank | S4: Original title
A5: 1 | B5: HN | C5: Small businesses struggle with repetitive, rule-based accounting tasks. | D5: open | E5: 3 | F5: 3 | G5: 2 | H5: 3 | I5: 3 | J5: 2 | K5: =SUM(E5:J5) | L5: =IF(K5>=15,"Shortlist",IF(K5<10,"Drop","Middle")) | O5: =(E5<>'Score reasons'!C2)+(F5<>'Score reasons'!F2)+(G5<>'Score reasons'!I2)+(H5<>'Score reasons'!L2)+(I5<>'Score reasons'!O2)+(J5<>'Score reasons'!R2) | P5: 16 | Q5: 15 | R5: 1 | S5: Tell HN: AI coding is sexy, but accounting is the real low-hanging target
A6: 2 | B6: HN | C6: Founders manually split revenue into multiple accounts monthly. | D6: open | E6: 2 | F6: 3 | G6: 3 | H6: 3 | I6: 3 | J6: 2 | K6: =SUM(E6:J6) | L6: =IF(K6>=15,"Shortlist",IF(K6<10,"Drop","Middle")) | O6: =(E6<>'Score reasons'!C3)+(F6<>'Score reasons'!F3)+(G6<>'Score reasons'!I3)+(H6<>'Score reasons'!L3)+(I6<>'Score reasons'!O3)+(J6<>'Score reasons'!R3) | P6: 16 | Q6: 13 | R6: 8 | S6: Does "Zapier for payment automation" exist?
A7: 3 | B7: HN | C7: A family business uses a 1993-era TUI for core operations. | D7: open | E7: 3 | F7: 3 | G7: 3 | H7: 2 | I7: 3 | J7: 2 | K7: =SUM(E7:J7) | L7: =IF(K7>=15,"Shortlist",IF(K7<10,"Drop","Middle")) | O7: =(E7<>'Score reasons'!C4)+(F7<>'Score reasons'!F4)+(G7<>'Score reasons'!I4)+(H7<>'Score reasons'!L4)+(I7<>'Score reasons'!O4)+(J7<>'Score reasons'!R4) | P7: 16 | Q7: 12 | R7: 9 | S7: My family business runs on a 1993-era text-based-UI (TUI). Anybody else?
A8: 4 | B8: HN | C8: Senior engineers struggle to understand historical engineering decisions in a codebase. | D8: open | E8: 3 | F8: 3 | G8: 3 | H8: 3 | I8: 2 | J8: 2 | K8: =SUM(E8:J8) | L8: =IF(K8>=15,"Shortlist",IF(K8<10,"Drop","Middle")) | O8: =(E8<>'Score reasons'!C5)+(F8<>'Score reasons'!F5)+(G8<>'Score reasons'!I5)+(H8<>'Score reasons'!L5)+(I8<>'Score reasons'!O5)+(J8<>'Score reasons'!R5) | P8: 16 | Q8: 11 | R8: 11 | S8: How do you capture WHY engineering decisions were made, not just what?
A9: 5 | B9: HN | C9: Users face increasing barriers to access online services due to overzealous security measures. | D9: open | E9: 2 | F9: 3 | G9: 3 | H9: 3 | I9: 3 | J9: 2 | K9: =SUM(E9:J9) | L9: =IF(K9>=15,"Shortlist",IF(K9<10,"Drop","Middle")) | O9: =(E9<>'Score reasons'!C6)+(F9<>'Score reasons'!F6)+(G9<>'Score reasons'!I6)+(H9<>'Score reasons'!L6)+(I9<>'Score reasons'!O6)+(J9<>'Score reasons'!R6) | P9: 16 | Q9: 10 | R9: 15 | S9: Internet is no longer accessible?
A10: 6 | B10: HN | C10: Resellers waste time researching items and miss deals due to slow analysis. | D10: open | E10: 1 | F10: 3 | G10: 3 | H10: 3 | I10: 3 | J10: 2 | K10: =SUM(E10:J10) | L10: =IF(K10>=15,"Shortlist",IF(K10<10,"Drop","Middle")) | O10: =(E10<>'Score reasons'!C7)+(F10<>'Score reasons'!F7)+(G10<>'Score reasons'!I7)+(H10<>'Score reasons'!L7)+(I10<>'Score reasons'!O7)+(J10<>'Score reasons'!R7) | P10: 15 | Q10: 12 | R10: 10 | S10: Built an AI-powered profit calculator and inventory tracker app for resellers
A11: 7 | B11: HN | C11: Principal engineers struggle to trust AI with design decisions in complex codebases. | D11: open | E11: 2 | F11: 3 | G11: 2 | H11: 3 | I11: 3 | J11: 2 | K11: =SUM(E11:J11) | L11: =IF(K11>=15,"Shortlist",IF(K11<10,"Drop","Middle")) | O11: =(E11<>'Score reasons'!C8)+(F11<>'Score reasons'!F8)+(G11<>'Score reasons'!I8)+(H11<>'Score reasons'!L8)+(I11<>'Score reasons'!O8)+(J11<>'Score reasons'!R8) | P11: 15 | Q11: 11 | R11: 12 | S11: Is AI slowing you down?
A12: 8 | B12: HN | C12: Network engineers struggle to maintain accurate, up-to-date documentation of network relationships. | D12: open | E12: 1 | F12: 3 | G12: 3 | H12: 3 | I12: 3 | J12: 2 | K12: =SUM(E12:J12) | L12: =IF(K12>=15,"Shortlist",IF(K12<10,"Drop","Middle")) | O12: =(E12<>'Score reasons'!C9)+(F12<>'Score reasons'!F9)+(G12<>'Score reasons'!I9)+(H12<>'Score reasons'!L9)+(I12<>'Score reasons'!O9)+(J12<>'Score reasons'!R9) | P12: 15 | Q12: 10 | R12: 16 | S12: Why is network documentation still a scavenger hunt for the truth?
A13: 9 | B13: HN | C13: Freelancers lose time and revenue due to fragmented tools and workflows. | D13: open | E13: 1 | F13: 3 | G13: 3 | H13: 3 | I13: 3 | J13: 2 | K13: =SUM(E13:J13) | L13: =IF(K13>=15,"Shortlist",IF(K13<10,"Drop","Middle")) | O13: =(E13<>'Score reasons'!C10)+(F13<>'Score reasons'!F10)+(G13<>'Score reasons'!I10)+(H13<>'Score reasons'!L10)+(I13<>'Score reasons'!O10)+(J13<>'Score reasons'!R10) | P13: 15 | Q13: 10 | R13: 17 | S13: Freelancers are losing ~30% of their time and revenue to tool fragmentation
A14: 10 | B14: HN | C14: GitHub users experience inconsistent release visibility and UI errors across regions. | D14: open | E14: 1 | F14: 3 | G14: 3 | H14: 3 | I14: 3 | J14: 2 | K14: =SUM(E14:J14) | L14: =IF(K14>=15,"Shortlist",IF(K14<10,"Drop","Middle")) | O14: =(E14<>'Score reasons'!C11)+(F14<>'Score reasons'!F11)+(G14<>'Score reasons'!I11)+(H14<>'Score reasons'!L11)+(I14<>'Score reasons'!O11)+(J14<>'Score reasons'!R11) | P14: 15 | Q14: 9 | R14: 18 | S14: Is GitHub becoming more and more unstable?
A15: 11 | B15: HN | C15: Developers struggle to maintain accurate call state and real-time billing in browser-based VoIP. | D15: open | E15: 1 | F15: 3 | G15: 3 | H15: 3 | I15: 3 | J15: 2 | K15: =SUM(E15:J15) | L15: =IF(K15>=15,"Shortlist",IF(K15<10,"Drop","Middle")) | O15: =(E15<>'Score reasons'!C12)+(F15<>'Score reasons'!F12)+(G15<>'Score reasons'!I12)+(H15<>'Score reasons'!L12)+(I15<>'Score reasons'!O12)+(J15<>'Score reasons'!R12) | P15: 15 | Q15: 9 | R15: 19 | S15: Building CallSpark (browser based VoIP): what I learned and what caused pain
A16: 12 | B16: HN | C16: Architectural startups need automated 3D geometry extraction from 2D floor plans. | D16: open | E16: 1 | F16: 3 | G16: 3 | H16: 3 | I16: 3 | J16: 2 | K16: =SUM(E16:J16) | L16: =IF(K16>=15,"Shortlist",IF(K16<10,"Drop","Middle")) | O16: =(E16<>'Score reasons'!C13)+(F16<>'Score reasons'!F13)+(G16<>'Score reasons'!I13)+(H16<>'Score reasons'!L13)+(I16<>'Score reasons'!O13)+(J16<>'Score reasons'!R13) | P16: 15 | Q16: 9 | R16: 20 | S16: Instance segmentation model that extracts 3D geometry from 2D floor plans
... A24: 20 | B24: USAspending | C24: Agencies repeatedly buy "legacy system modernization" services | D24: open | E24: 1 | F24: 2 | G24: 1 | H24: 3 | I24: 1 | J24: 3 | K24: =SUM(E24:J24) | L24: =IF(K24>=15,"Shortlist",IF(K24<10,"Drop","Middle")) | O24: =(E24<>'Score reasons'!C21)+(F24<>'Score reasons'!F21)+(G24<>'Score reasons'!I21)+(H24<>'Score reasons'!L21)+(I24<>'Score reasons'!O21)+(J24<>'Score reasons'!R21) | P24: 11 | Q24: 11 | R24: 14 | S24: Agencies repeatedly buy "legacy system modernization" services

Sheet Score reasons
A1: # | B1: Problem | C1: Freq (orig) | D1: Freq method | E1: Freq reason | F1: Pain (orig) | G1: Pain method | H1: Pain reason | I1: Messy (orig) | J1: Messy method | K1: Messy reason | L1: Backend (orig) | M1: Backend method | N1: Backend reason | O1: Reach (orig) | P1: Reach method | Q1: Reach reason | R1: Free data (orig) | S1: Free data method | T1: Free data reason
A2: 1 | B2: Small businesses struggle with repetitive, rule-based accounting tasks. | C2: 3 | D2: rule | E2: 55 comments, matched 1 phrases | F2: 3 | G2: qwen3:8b (judge-v1) | H2: The post states: 'Humans hate this work. Software loves it.' | I2: 2 | J2: qwen3:8b (judge-v1) | K2: The post mentions: 'normalize data from banks / cards / invoices'. | L2: 3 | M2: qwen3:8b (judge-v1) | N2: The post describes: 'apply deterministic or configurable rules, surface exceptions'. | O2: 3 | P2: qwen3:8b (judge-v1) | Q2: The post targets: 'small-business level accounting teams'. | R2: 2 | S2: rule | T2: default: unknown, assume partly public
A3: 2 | B3: Founders manually split revenue into multiple accounts monthly. | C3: 2 | D3: rule | E3: 18 comments, matched 1 phrases | F3: 3 | G3: qwen3:8b (judge-v1) | H3: Spends 3 hours/month on manual splitting $15K revenue. | I3: 3 | J3: qwen3:8b (judge-v1) | K3: Data spread across Stripe, Zapier, manual scripts, and escrow. | L3: 3 | M3: qwen3:8b (judge-v1) | N3: Involves real ingestion, matching, and storage of financial flows. | O3: 3 | P3: qwen3:8b (judge-v1) | Q3: Specific group: founders with revenue splitting needs. Can message 5 via forums or networks. | R3: 2 | S3: rule | T3: default: unknown, assume partly public
A4: 3 | B4: A family business uses a 1993-era TUI for core operations. | C4: 3 | D4: rule | E4: 309 comments, matched 1 phrases | F4: 3 | G4: qwen3:8b (judge-v1) | H4: They've spent years maintaining a brittle system with no modern alternatives. | I4: 3 | J4: qwen3:8b (judge-v1) | K4: Data is spread across multiple systems with no shared key (XP machine, TUI, modern scripts). | L4: 2 | M4: qwen3:8b (judge-v1) | N4: Involves data ingestion, matching, and storage via scripts and telnet. | O4: 3 | P4: qwen3:8b (judge-v1) | Q4: Specific group: family businesses using legacy TUI systems for core operations. | R4: 2 | S4: rule | T4: default: unknown, assume partly public
A5: 4 | B5: Senior engineers struggle to understand historical engineering decisions in a codebase. | C5: 3 | D5: rule | E5: 64 comments, matched 1 phrases | F5: 3 | G5: qwen3:8b (judge-v1) | H5: He spent 3 weeks playing code archaeologist to find reasoning behind code decisions. | I5: 3 | J5: qwen3:8b (judge-v1) | K5: Answers were buried in closed PRs, Slack threads, and departed engineers' knowledge. | L5: 3 | M5: qwen3:8b (judge-v1) | N5: We tried ADRs, PR templates, and Notion docs, all manually maintained and outdated. | O5: 2 | P5: qwen3:8b (judge-v1) | Q5: Curious how teams at HN handle this: 1. Do you have a system that actually works long-term? 2. Has anyone automated any part of this? 3. Or is everyone quietly suffering through this on every new hire? | R5: 2 | S5: rule | T5: default: unknown, assume partly public
A6: 5 | B6: Users face increasing barriers to access online services due to overzealous security measures. | C6: 2 | D6: rule | E6: 25 comments, matched 1 phrases | F6: 3 | G6: qwen3:8b (judge-v1) | H6: Website blocks copy paste, so you have to manually type everything. | I6: 3 | J6: qwen3:8b (judge-v1) | K6: Registering a new Google account requires a phone number, and I also need to install app to prove I am not a bot. | L6: 3 | M6: qwen3:8b (judge-v1) | N6: MFA codes sent to my phone do not seem to work properly. | O6: 3 | P6: qwen3:8b (judge-v1) | Q6: Everyone assumes you are bot. /no_really | R6: 2 | S6: rule | T6: default: unknown, assume partly public
A7: 6 | B7: Resellers waste time researching items and miss deals due to slow analysis. | C7: 1 | D7: rule | E7: 0 comments, matched 1 phrase | F7: 3 | G7: qwen3:8b (judge-v1) | H7: You waste time and miss deals while researching (someone else grabs it). | I7: 3 | J7: qwen3:8b (judge-v1) | K7: Researching items takes ~5 minutes per item You buy blindly and hope for the best | L7: 3 | M7: qwen3:8b (judge-v1) | N7: AI identifies the item → Get instant analysis: Profit potential after all fees ROI percentage | O7: 3 | P7: qwen3:8b (judge-v1) | Q7: Active users in flipping community What I'm Working On More accurate valuations for niche items | R7: 2 | S7: rule | T7: default: unknown, assume partly public
A8: 7 | B8: Principal engineers struggle to trust AI with design decisions in complex codebases. | C8: 2 | D8: rule | E8: 13 comments, matched 1 phrases | F8: 3 | G8: qwen3:8b (judge-v1) | H8: Work required to build detailed specs and review AI changes is explicitly stated as time-consuming. | I8: 2 | J8: qwen3:8b (judge-v1) | K8: Codebase is described as 'massive' and requires precise updates, implying inconsistent or missing data. | L8: 3 | M8: qwen3:8b (judge-v1) | N8: Involves 'agents to build complex features' and 'updating codebase', indicating real ingestion, matching, and storage. | O8: 3 | P8: qwen3:8b (judge-v1) | Q8: Specific group: principal engineers working on large, complex codebases with AI integration. | R8: 2 | S8: rule | T8: default: unknown, assume partly public
A9: 8 | B9: Network engineers struggle to maintain accurate, up-to-date documentation of network relationships. | C9: 1 | D9: rule | E9: 0 comments, matched 1 phrase | F9: 3 | G9: qwen3:8b (judge-v1) | H9: ‘Eventually the real topology lives in people’s heads and you get the classic: “Don’t touch that!”’ | I9: 3 | J9: qwen3:8b (judge-v1) | K9: ‘Whatever you call the “source of truth” [...] almost always diverges from the running state.’ | L9: 3 | M9: qwen3:8b (judge-v1) | N9: ‘Most teams still end up maintaining heavy documents, or growing forest of scripts to parse all sorts of information’ | O9: 3 | P9: qwen3:8b (judge-v1) | Q9: ‘I’d love to listen your “this never works” stories’ implies a specific group of network engineers and DevOps professionals. | R9: 2 | S9: rule | T9: default: unknown, assume partly public
A10: 9 | B10: Freelancers lose time and revenue due to fragmented tools and workflows. | C10: 1 | D10: rule | E10: 1 comments, matched 1 phrase | F10: 3 | G10: qwen3:8b (judge-v1) | H10: One freelancer lost ₹70,000 in a client dispute due to poor tracking. | I10: 3 | J10: qwen3:8b (judge-v1) | K10: Projects sit in Gmail, portfolios in Notion, payments on random links, and invoices in spreadsheets. | L10: 3 | M10: qwen3:8b (judge-v1) | N10: Involves real ingestion, matching, and storage of data across systems. | O10: 3 | P10: qwen3:8b (judge-v1) | Q10: A specific group: freelancers and small agency owners who manage client work. | R10: 2 | S10: rule | T10: default: unknown, assume partly public
A11: 10 | B11: GitHub users experience inconsistent release visibility and UI errors across regions. | C11: 1 | D11: rule | E11: 4 comments, matched 1 phrase | F11: 3 | G11: qwen3:8b (judge-v1) | H11: Users had to unpublish and re-publish, and re-test manually due to UI issues. | I11: 3 | J11: qwen3:8b (judge-v1) | K11: Release visibility differed by region, and UI issues were inconsistent across systems. | L11: 3 | M11: qwen3:8b (judge-v1) | N11: Involves real ingestion, matching, and storage of release data across global systems. | O11: 3 | P11: qwen3:8b (judge-v1) | Q11: Specific group: software teams using GitHub for release management and CI/CD. | R11: 2 | S11: rule | T11: default: unknown, assume partly public
A12: 11 | B12: Developers struggle to maintain accurate call state and real-time billing in browser-based VoIP. | C12: 1 | D12: rule | E12: 0 comments, matched 1 phrase | F12: 3 | G12: qwen3:8b (judge-v1) | H12: The post states 'you quickly run into edge cases' and 'reconcile without double-charging'. | I12: 3 | J12: qwen3:8b (judge-v1) | K12: Call state is 'spread across several systems with no shared key' due to UI and backend disconnection. | L12: 3 | M12: qwen3:8b (judge-v1) | N12: The post describes 'real ingestion, matching, and storage' with a periodic worker and reconciliation. | O12: 3 | P12: qwen3:8b (judge-v1) | Q12: The post targets 'developers building real-time billing for VoIP' who can be found in relevant communities or job roles. | R12: 2 | S12: rule | T12: default: unknown, assume partly public
A13: 12 | B13: Architectural startups need automated 3D geometry extraction from 2D floor plans. | C13: 1 | D13: rule | E13: 0 comments, matched 1 phrase | F13: 3 | G13: qwen3:8b (judge-v1) | H13: They rely on human data entry, which is time-consuming and costly. | I13: 3 | J13: qwen3:8b (judge-v1) | K13: 2D floor plans are messy, highly occluded, and contain intersecting elements. | L13: 3 | M13: qwen3:8b (judge-v1) | N13: Involves real ingestion, matching, and storage of structured 3D geometry data. | O13: 3 | P13: qwen3:8b (judge-v1) | Q13: Specific group: PropTech startups and product builders in that space. | R13: 2 | S13: rule | T13: default: unknown, assume partly public
... A21: 20 | B21: Agencies repeatedly buy "legacy system modernization" services | C21: 1 | D21: rule | E21: 2 agencies, 2 awards | F21: 2 | G21: rule | H21: $3.0M spent in window | I21: 1 | J21: rule | K21: 0 vendor names with multiple spellings | L21: 3 | M21: rule | N21: data-processing service by keyword choice | O21: 1 | P21: rule | Q21: government buyers are hard to reach (guess; vendors may be easier) | R21: 3 | S21: rule | T21: USAspending is public

Sheet Summary
A1: Phase 0 summary
A2: Inputs (fill in)
A3: Manual search minutes before abandoning | C3: From your timer: start 10:39 PM on 2026-10-03 to when you stopped. Enter minutes.
A4: Minutes spent reviewing this workbook | C4: Start a timer when you open this file; enter minutes when done.
A5: Results (formulas)
A6: Candidates | B6: =COUNTA(Candidates!$C$5:$C$24) | C6: Rows on the Candidates sheet.
A7: Labeled | B7: =COUNTIF(Candidates!$M$5:$M$24,"yes")+COUNTIF(Candidates!$M$5:$M$24,"maybe")+COUNTIF(Candidates!$M$5:$M$24,"no") | C7: Rows with Pursue? filled in.
A8: Pursue = yes | B8: =COUNTIF(Candidates!$M$5:$M$24,"yes")
A9: Pursue = maybe | B9: =COUNTIF(Candidates!$M$5:$M$24,"maybe")
A10: Pursue = no | B10: =COUNTIF(Candidates!$M$5:$M$24,"no")
A11: Precision of top 20 (yes ÷ candidates) | B11: =IF(B6=0,0,B8/B6) | C11: REQUIREMENTS §9: share of the top 20 you label interesting.
A12: Precision, lenient (yes + maybe ÷ candidates) | B12: =IF(B6=0,0,(B8+B9)/B6)
A13: Top 10 by scout ranking: share yes | B13: =COUNTIFS(Candidates!$A$5:$A$24,"<=10",Candidates!$M$5:$M$24,"yes")/10 | C13: Hybrid ranking (rows 1–10 as delivered).
A14: Top 10 by rules-only ranking: share yes | B14: =COUNTIFS(Candidates!$R$5:$R$24,"<=10",Candidates!$M$5:$M$24,"yes")/10 | C14: Same rows ranked by rules only. Higher than the line above means the model didn't help.
A15: Shortlist (Total ≥ 15) after your edits | B15: =COUNTIF(Candidates!$K$5:$K$24,">=15")
A16: Scores you changed | B16: =SUM(Candidates!$O$5:$O$24) | C16: FR-18: overrides are labels for measuring scoring quality.
A17: Hours per qualified opportunity (assisted) | B17: =IF(B8=0,0,B4/60/B8) | C17: Review minutes ÷ 60 ÷ yes count. 0 until you enter minutes and label.
A18: Run info
A19: Generated | B19: 2026-10-04T13:58:46.460Z
A20: Scoring method | B20: Hybrid (ADR-002): Pain, Messy, Backend, Reachable for HN by qwen3:8b (prompt judge-v1) on the top 271 HN items by rule score; everything else by rules.

Sheet Rubric
A1: Criterion | B1: 1 | C1: 2 | D1: 3 | E1: Scored by
A2: Frequency | B2: Seen once | C2: 2–3 times, or in 2 places | D2: Recurring across sources or many comments | E2: Rule
A3: Pain | B3: Annoyance, no cost stated | C3: Time or money cost implied | D3: Hours or dollars stated | E3: Model (HN), rule (USAspending)
A4: Messy data | B4: One clean source | C4: Some variants or missing fields | D4: Several sources, no shared key | E4: Model (HN), rule (USAspending)
A5: Backend weight | B5: Mostly UI / forms | C5: Some ingestion or matching | D5: Real ingestion, matching, storage | E5: Model (HN), rule (USAspending)
A6: Reachable | B6: Can't say where they are | C6: Know a community | D6: Could message 5 this week | E6: Model (HN), rule (USAspending)
A7: Free data | B7: Needs paid/private data | C7: Partly public | D7: Prototype fully on public data | E7: Rule
A8: Total | B8: 6–18 | C8: ≥ 15 = Shortlist | D8: < 10 = Drop
A10: Higher is better: 3 is the strongest score on every criterion, 1 the weakest.
