Workbook

Sheet Candidates
A1: Phase 0 candidates
A2: You can edit the score columns (1–3), Pursue? and Notes (light blue). Total, Band, and the Summary sheet recalculate. Example: Pursue? = maybe, Notes = "talk to 2 bookkeepers before deciding". Grey columns are the scout's original output for comparison. Scorer v2 rows (Buyer filled in): Total leaves out Freq (popularity only) and any "unsupported" score (its quote was not found in the post); Band is Shortlist when all four gates pass, ranked by Total.
A3: Colors: higher is better. Green = good (score 3, Total 15+, Shortlist). Yellow = neutral (score 2, Total 10–14). Red = weak (score 1, Total under 10, Drop).
A4: # | B4: Source | C4: Problem | D4: Link | E4: Freq | F4: Pain | G4: Messy | H4: Backend | I4: Reach | J4: Buyer | K4: Free data | L4: Total | M4: Band | N4: Pursue? | O4: Notes | P4: Scores changed | Q4: Scout total | R4: Rules-only total | S4: Rules-only rank | T4: G1 current | U4: G2 need | V4: G3 not trivial | W4: G4 author has it | X4: Evidence (valid quotes) | Y4: Popularity (comments) | Z4: Original title
A5: 1 | B5: City contracts | C5: City HR departments developing, administering, and securing civil service hiring exams. | D5: open | E5: 1 | F5: 2 | G5: 2 | H5: 3 | I5: 3 | J5: 3 | K5: 3 | L5: =SUM(F5:K5) | M5: =IF(AND(T5="pass",U5="pass",V5="pass",W5="pass",COUNTIF(F5:K5,"unsupported")=0),"Shortlist","Review") | P5: =(E5<>'Score reasons'!C2)+(F5<>'Score reasons'!F2)+(G5<>'Score reasons'!I2)+(H5<>'Score reasons'!L2)+(I5<>'Score reasons'!O2)+(J5<>'Score reasons'!R2)+(K5<>'Score reasons'!U2) | Q5: 16 | R5: 8 | S5: 17 | T5: pass | U5: pass | V5: pass | W5: pass | X5: 9/9 | Y5: 0 | Z5: [Chicago · DEPARTMENT OF HUMAN RESOURCES] MASTER CONSULTING AGREEMENT FOR HUMAN RESOURCE TESTING SERVICES- CATEGORY 1: DEVELOPMENT OF
A6: 2 | B6: City contracts | C6: City clerk staff need a system to intake and manage legislative documents. | D6: open | E6: 1 | F6: 2 | G6: 2 | H6: 3 | I6: 2 | J6: 3 | K6: 3 | L6: =SUM(F6:K6) | M6: =IF(AND(T6="pass",U6="pass",V6="pass",W6="pass",COUNTIF(F6:K6,"unsupported")=0),"Shortlist","Review") | P6: =(E6<>'Score reasons'!C3)+(F6<>'Score reasons'!F3)+(G6<>'Score reasons'!I3)+(H6<>'Score reasons'!L3)+(I6<>'Score reasons'!O3)+(J6<>'Score reasons'!R3)+(K6<>'Score reasons'!U3) | Q6: 15 | R6: 8 | S6: 18 | T6: pass | U6: pass | V6: pass | W6: pass | X6: 9/9 | Y6: 0 | Z6: [Chicago · OFFICE OF CITY CLERK] TECHNOLOGY AND SERVICES RELATING TO THE LEGISLATIVE MANAGEMENT DOCUMENT INTAKE SYSTEM WITH
A7: 3 | B7: City contracts | C7: City department staff needing to store, retrieve, and manage large volumes of city records. | D7: open | E7: 1 | F7: 2 | G7: 2 | H7: 3 | I7: 2 | J7: 3 | K7: 3 | L7: =SUM(F7:K7) | M7: =IF(AND(T7="pass",U7="pass",V7="pass",W7="pass",COUNTIF(F7:K7,"unsupported")=0),"Shortlist","Review") | P7: =(E7<>'Score reasons'!C4)+(F7<>'Score reasons'!F4)+(G7<>'Score reasons'!I4)+(H7<>'Score reasons'!L4)+(I7<>'Score reasons'!O4)+(J7<>'Score reasons'!R4)+(K7<>'Score reasons'!U4) | Q7: 15 | R7: 8 | S7: 19 | T7: pass | U7: pass | V7: pass | W7: pass | X7: 9/9 | Y7: 0 | Z7: [Chicago · DEPARTMENT OF FLEET AND FACILITY MANAGEMENT] RECORDS STORAGE AND RELATED RECORDS MANAGEMENT SERVICES- CITY OF CHICAGO
A8: 4 | B8: City contracts | C8: City HR departments needing background checks and reporting for job candidates. | D8: open | E8: 1 | F8: 1 | G8: 2 | H8: 3 | I8: 3 | J8: 3 | K8: 3 | L8: =SUM(F8:K8) | M8: =IF(AND(T8="pass",U8="pass",V8="pass",W8="pass",COUNTIF(F8:K8,"unsupported")=0),"Shortlist","Review") | P8: =(E8<>'Score reasons'!C5)+(F8<>'Score reasons'!F5)+(G8<>'Score reasons'!I5)+(H8<>'Score reasons'!L5)+(I8<>'Score reasons'!O5)+(J8<>'Score reasons'!R5)+(K8<>'Score reasons'!U5) | Q8: 15 | R8: 8 | S8: 20 | T8: pass | U8: pass | V8: pass | W8: pass | X8: 9/9 | Y8: 0 | Z8: [Chicago · ] CANDIDATE BACKGROUND INVESTIGATION & REPORTING SERVICES SCOPE CHANGE
A9: 5 | B9: City contracts | C9: NYC Finance must process, print, and mail violation summonses at large volume. | D9: open | E9: 1 | F9: 2 | G9: 2 | H9: 3 | I9: 2 | J9: 3 | K9: 3 | L9: =SUM(F9:K9) | M9: =IF(AND(T9="pass",U9="pass",V9="pass",W9="pass",COUNTIF(F9:K9,"unsupported")=0),"Shortlist","Review") | P9: =(E9<>'Score reasons'!C6)+(F9<>'Score reasons'!F6)+(G9<>'Score reasons'!I6)+(H9<>'Score reasons'!L6)+(I9<>'Score reasons'!O6)+(J9<>'Score reasons'!R6)+(K9<>'Score reasons'!U6) | Q9: 15 | R9: 8 | S9: 21 | T9: pass | U9: pass | V9: pass | W9: pass | X9: 9/9 | Y9: 0 | Z9: [New York City · Finance] Data Processing, Printing & Mailing Services for Violation Summonses
A10: 6 | B10: City contracts | C10: City family services staff needing annual homeless point-in-time count research and analysis. | D10: open | E10: 1 | F10: 1 | G10: 2 | H10: 2 | I10: 2 | J10: 2 | K10: 3 | L10: =SUM(F10:K10) | M10: =IF(AND(T10="pass",U10="pass",V10="pass",W10="pass",COUNTIF(F10:K10,"unsupported")=0),"Shortlist","Review") | P10: =(E10<>'Score reasons'!C7)+(F10<>'Score reasons'!F7)+(G10<>'Score reasons'!I7)+(H10<>'Score reasons'!L7)+(I10<>'Score reasons'!O7)+(J10<>'Score reasons'!R7)+(K10<>'Score reasons'!U7) | Q10: 12 | R10: 8 | S10: 22 | T10: pass | U10: pass | V10: pass | W10: pass | X10: 9/9 | Y10: 0 | Z10: [Chicago · DEPARTMENT OF FAMILY AND SUPPORT SERVICES] HOMELESS POINT IN TIME RESEARCH AND ANALYSIS
A11: 7 | B11: City contracts | C11: City facility managers overseeing riverwalk property leases and concession vendors. | D11: open | E11: 1 | F11: 1 | G11: 2 | H11: 2 | I11: 2 | J11: 2 | K11: 3 | L11: =SUM(F11:K11) | M11: =IF(AND(T11="pass",U11="pass",V11="pass",W11="pass",COUNTIF(F11:K11,"unsupported")=0),"Shortlist","Review") | P11: =(E11<>'Score reasons'!C8)+(F11<>'Score reasons'!F8)+(G11<>'Score reasons'!I8)+(H11<>'Score reasons'!L8)+(I11<>'Score reasons'!O8)+(J11<>'Score reasons'!R8)+(K11<>'Score reasons'!U8) | Q11: 12 | R11: 8 | S11: 23 | T11: pass | U11: pass | V11: pass | W11: pass | X11: 9/9 | Y11: 0 | Z11: [Chicago · DEPARTMENT OF FLEET AND FACILITY MANAGEMENT] TRANSFER FROM PO 60672 (MB REAL ESTATE) PROPERTY AND CONCESSIONS MANAGEMENT ON
A12: 8 | B12: City contracts | C12: HRA and DHS must translate client notices and materials into many languages. | D12: open | E12: 1 | F12: 2 | G12: 2 | H12: 3 | I12: 2 | J12: 3 | K12: 3 | L12: =SUM(F12:K12) | M12: =IF(AND(T12="pass",U12="pass",V12="pass",W12="pass",COUNTIF(F12:K12,"unsupported")=0),"Shortlist","Review") | P12: =(E12<>'Score reasons'!C9)+(F12<>'Score reasons'!F9)+(G12<>'Score reasons'!I9)+(H12<>'Score reasons'!L9)+(I12<>'Score reasons'!O9)+(J12<>'Score reasons'!R9)+(K12<>'Score reasons'!U9) | Q12: 15 | R12: 9 | S12: 13 | T12: unsupported | U12: pass | V12: pass | W12: pass | X12: 8/9 | Y12: 0 | Z12: [New York City · Dept. of Social Svcs/Human Resources Administration] The Human Resources Administration, and the Department of Homeless Services (DSS/HRA/DHS) prefers
A13: 9 | B13: City contracts | C13: Chicago Department of Finance needs cashiering and customer payment services handled. | D13: open | E13: 1 | F13: 1 | G13: 2 | H13: 3 | I13: 2 | J13: 3 | K13: 3 | L13: =SUM(F13:K13) | M13: =IF(AND(T13="pass",U13="pass",V13="pass",W13="pass",COUNTIF(F13:K13,"unsupported")=0),"Shortlist","Review") | P13: =(E13<>'Score reasons'!C10)+(F13<>'Score reasons'!F10)+(G13<>'Score reasons'!I10)+(H13<>'Score reasons'!L10)+(I13<>'Score reasons'!O10)+(J13<>'Score reasons'!R10)+(K13<>'Score reasons'!U10) | Q13: 14 | R13: 8 | S13: 24 | T13: unsupported | U13: pass | V13: pass | W13: pass | X13: 8/9 | Y13: 0 | Z13: [Chicago · DEPARTMENT OF FINANCE] TRANSFER FROM PO # 71921 PROFESSIONAL CASHIERING AND RELATED CUSTOMER SERVICES
A14: 10 | B14: City contracts | C14: Law department staff needing transcripts of depositions, hearings, and meetings. | D14: open | E14: 1 | F14: 1 | G14: 2 | H14: 2 | I14: 2 | J14: 3 | K14: 3 | L14: =SUM(F14:K14) | M14: =IF(AND(T14="pass",U14="pass",V14="pass",W14="pass",COUNTIF(F14:K14,"unsupported")=0),"Shortlist","Review") | P14: =(E14<>'Score reasons'!C11)+(F14<>'Score reasons'!F11)+(G14<>'Score reasons'!I11)+(H14<>'Score reasons'!L11)+(I14<>'Score reasons'!O11)+(J14<>'Score reasons'!R11)+(K14<>'Score reasons'!U11) | Q14: 13 | R14: 8 | S14: 25 | T14: unsupported | U14: pass | V14: pass | W14: pass | X14: 8/9 | Y14: 0 | Z14: [Chicago · DEPARTMENT OF LAW] NON-TARGET MARKET AGREEMENT, COURT REPORTING & TRANSCRIPTION SVCS, AREA 2: BUS AFFAIRS
A15: 11 | B15: City contracts | C15: Health department facilities staff needing fire alarm monitoring and inspection across many buildings. | D15: open | E15: 1 | F15: 1 | G15: 2 | H15: 2 | I15: 2 | J15: 3 | K15: 3 | L15: =SUM(F15:K15) | M15: =IF(AND(T15="pass",U15="pass",V15="pass",W15="pass",COUNTIF(F15:K15,"unsupported")=0),"Shortlist","Review") | P15: =(E15<>'Score reasons'!C12)+(F15<>'Score reasons'!F12)+(G15<>'Score reasons'!I12)+(H15<>'Score reasons'!L12)+(I15<>'Score reasons'!O12)+(J15<>'Score reasons'!R12)+(K15<>'Score reasons'!U12) | Q15: 13 | R15: 8 | S15: 26 | T15: unsupported | U15: pass | V15: pass | W15: pass | X15: 8/9 | Y15: 0 | Z15: [New York City · Health and Mental Hygiene] Monitoring, Repair and Inspection of Fire Alarm System. Pursuant to Procurement Policy
A16: 12 | B16: City contracts | C16: Airport and emergency management staff need weather forecasts and alerts for operations. | D16: open | E16: 1 | F16: 2 | G16: 2 | H16: 3 | I16: 2 | J16: unsupported | K16: 3 | L16: =SUM(F16:K16) | M16: =IF(AND(T16="pass",U16="pass",V16="pass",W16="pass",COUNTIF(F16:K16,"unsupported")=0),"Shortlist","Review") | P16: =(E16<>'Score reasons'!C13)+(F16<>'Score reasons'!F13)+(G16<>'Score reasons'!I13)+(H16<>'Score reasons'!L13)+(I16<>'Score reasons'!O13)+(J16<>'Score reasons'!R13)+(K16<>'Score reasons'!U13) | Q16: 12 | R16: 8 | S16: 27 | T16: pass | U16: pass | V16: pass | W16: pass | X16: 8/9 | Y16: 0 | Z16: [Chicago · CHICAGO DEPARTMENT OF AVIATION] Weather Forecasting, Alerts and Data Services for Chicago Department of Aviation and
A17: 13 | B17: City contracts | C17: ACS HR needs pre-employment drug, medical, and fitness testing handled for new hires. | D17: open | E17: 1 | F17: 1 | G17: 1 | H17: 2 | I17: 2 | J17: 3 | K17: 3 | L17: =SUM(F17:K17) | M17: =IF(AND(T17="pass",U17="pass",V17="pass",W17="pass",COUNTIF(F17:K17,"unsupported")=0),"Shortlist","Review") | P17: =(E17<>'Score reasons'!C14)+(F17<>'Score reasons'!F14)+(G17<>'Score reasons'!I14)+(H17<>'Score reasons'!L14)+(I17<>'Score reasons'!O14)+(J17<>'Score reasons'!R14)+(K17<>'Score reasons'!U14) | Q17: 12 | R17: 8 | S17: 28 | T17: unsupported | U17: pass | V17: pass | W17: pass | X17: 8/9 | Y17: 0 | Z17: [New York City · Administration for Children's Services] Drug, Alcohol, Medical and Fitness Testing for New Hires Renewal #2. ACS'
A18: 14 | B18: City contracts | C18: NYC Parks needs ash trees treated and pruned against Emerald Ash Borer infestation. | D18: open | E18: 1 | F18: 2 | G18: 1 | H18: 1 | I18: 2 | J18: 2 | K18: 3 | L18: =SUM(F18:K18) | M18: =IF(AND(T18="pass",U18="pass",V18="pass",W18="pass",COUNTIF(F18:K18,"unsupported")=0),"Shortlist","Review") | P18: =(E18<>'Score reasons'!C15)+(F18<>'Score reasons'!F15)+(G18<>'Score reasons'!I15)+(H18<>'Score reasons'!L15)+(I18<>'Score reasons'!O15)+(J18<>'Score reasons'!R15)+(K18<>'Score reasons'!U15) | Q18: 11 | R18: 9 | S18: 14 | T18: unsupported | U18: pass | V18: pass | W18: pass | X18: 8/9 | Y18: 0 | Z18: [New York City · Parks and Recreation] EAB in Brooklyn and Staten Island. The work to be performed under
A19: 15 | B19: City contracts | C19: City facilities staff needing witnessed, documented elevator and conveyance inspection testing. | D19: open | E19: 1 | F19: 1 | G19: 1 | H19: 2 | I19: 2 | J19: 2 | K19: 3 | L19: =SUM(F19:K19) | M19: =IF(AND(T19="pass",U19="pass",V19="pass",W19="pass",COUNTIF(F19:K19,"unsupported")=0),"Shortlist","Review") | P19: =(E19<>'Score reasons'!C16)+(F19<>'Score reasons'!F16)+(G19<>'Score reasons'!I16)+(H19<>'Score reasons'!L16)+(I19<>'Score reasons'!O16)+(J19<>'Score reasons'!R16)+(K19<>'Score reasons'!U16) | Q19: 11 | R19: 8 | S19: 29 | T19: unsupported | U19: pass | V19: pass | W19: pass | X19: 8/9 | Y19: 0 | Z19: [New York City · Citywide Administrative Services] Third Party Witnessing of Inspections for DLM and CAT 1 and CAT
A20: 16 | B20: HN | C20: Engineering teams lose decision rationale and make new hires spend weeks reconstructing it | D20: open | E20: 3 | F20: 3 | G20: 3 | H20: 3 | I20: 3 | J20: 2 | K20: 2 | L20: =SUM(F20:K20) | M20: =IF(AND(T20="pass",U20="pass",V20="pass",W20="pass",COUNTIF(F20:K20,"unsupported")=0),"Shortlist","Review") | P20: =(E20<>'Score reasons'!C17)+(F20<>'Score reasons'!F17)+(G20<>'Score reasons'!I17)+(H20<>'Score reasons'!L17)+(I20<>'Score reasons'!O17)+(J20<>'Score reasons'!R17)+(K20<>'Score reasons'!U17) | Q20: 16 | R20: 11 | S20: 8 | T20: pass | U20: pass | V20: pass | W20: pass | X20: 9/9 | Y20: 64 | Z20: How do you capture WHY engineering decisions were made, not just what?
A21: 17 | B21: HN | C21: Founder manually splits monthly revenue across co-founder, contractors, affiliates, and tax account. | D21: open | E21: 2 | F21: 3 | G21: 2 | H21: 3 | I21: 2 | J21: 2 | K21: 2 | L21: =SUM(F21:K21) | M21: =IF(AND(T21="pass",U21="pass",V21="pass",W21="pass",COUNTIF(F21:K21,"unsupported")=0),"Shortlist","Review") | P21: =(E21<>'Score reasons'!C18)+(F21<>'Score reasons'!F18)+(G21<>'Score reasons'!I18)+(H21<>'Score reasons'!L18)+(I21<>'Score reasons'!O18)+(J21<>'Score reasons'!R18)+(K21<>'Score reasons'!U18) | Q21: 14 | R21: 13 | S21: 7 | T21: pass | U21: pass | V21: pass | W21: pass | X21: 9/9 | Y21: 18 | Z21: Does "Zapier for payment automation" exist?
A22: 18 | B22: HN | C22: Builders of AI workflows must manually review hallucination-prone generated messages, emails, and invoices before sending. | D22: open | E22: 2 | F22: 2 | G22: 2 | H22: 3 | I22: 3 | J22: 2 | K22: 2 | L22: =SUM(F22:K22) | M22: =IF(AND(T22="pass",U22="pass",V22="pass",W22="pass",COUNTIF(F22:K22,"unsupported")=0),"Shortlist","Review") | P22: =(E22<>'Score reasons'!C19)+(F22<>'Score reasons'!F19)+(G22<>'Score reasons'!I19)+(H22<>'Score reasons'!L19)+(I22<>'Score reasons'!O19)+(J22<>'Score reasons'!R19)+(K22<>'Score reasons'!U19) | Q22: 14 | R22: 9 | S22: 15 | T22: pass | U22: pass | V22: pass | W22: pass | X22: 9/9 | Y22: 21 | Z22: AI hallucinate. Do you ever double check the output?
A23: 19 | B23: HN | C23: Developers using coding agents are overwhelmed reviewing the large volume of AI-generated PRs. | D23: open | E23: 1 | F23: 2 | G23: 2 | H23: 3 | I23: 3 | J23: 2 | K23: 2 | L23: =SUM(F23:K23) | M23: =IF(AND(T23="pass",U23="pass",V23="pass",W23="pass",COUNTIF(F23:K23,"unsupported")=0),"Shortlist","Review") | P23: =(E23<>'Score reasons'!C20)+(F23<>'Score reasons'!F20)+(G23<>'Score reasons'!I20)+(H23<>'Score reasons'!L20)+(I23<>'Score reasons'!O20)+(J23<>'Score reasons'!R20)+(K23<>'Score reasons'!U20) | Q23: 14 | R23: 8 | S23: 30 | T23: pass | U23: pass | V23: pass | W23: pass | X23: 9/9 | Y23: 1 | Z23: How do you manage PR review fatigue from coding agents?
A24: 20 | B24: HN | C24: A founder spends 20-40 minutes daily checking many separate apps each morning. | D24: open | E24: 1 | F24: 2 | G24: 3 | H24: 3 | I24: 2 | J24: 2 | K24: 2 | L24: =SUM(F24:K24) | M24: =IF(AND(T24="pass",U24="pass",V24="pass",W24="pass",COUNTIF(F24:K24,"unsupported")=0),"Shortlist","Review") | P24: =(E24<>'Score reasons'!C21)+(F24<>'Score reasons'!F21)+(G24<>'Score reasons'!I21)+(H24<>'Score reasons'!L21)+(I24<>'Score reasons'!O21)+(J24<>'Score reasons'!R21)+(K24<>'Score reasons'!U21) | Q24: 14 | R24: 7 | S24: 32 | T24: pass | U24: pass | V24: pass | W24: pass | X24: 9/9 | Y24: 4 | Z24: How do you manage your morning catch-up routine?
A25: 21 | B25: HN | C25: Automation builders must manually review LLM outputs for emails, SMS, and invoices due to hallucinations. | D25: open | E25: 1 | F25: 2 | G25: 2 | H25: 2 | I25: 3 | J25: 2 | K25: 2 | L25: =SUM(F25:K25) | M25: =IF(AND(T25="pass",U25="pass",V25="pass",W25="pass",COUNTIF(F25:K25,"unsupported")=0),"Shortlist","Review") | P25: =(E25<>'Score reasons'!C22)+(F25<>'Score reasons'!F22)+(G25<>'Score reasons'!I22)+(H25<>'Score reasons'!L22)+(I25<>'Score reasons'!O22)+(J25<>'Score reasons'!R22)+(K25<>'Score reasons'!U22) | Q25: 13 | R25: 10 | S25: 12 | T25: pass | U25: pass | V25: pass | W25: pass | X25: 9/9 | Y25: 5 | Z25: AI hallucinates. How do you keep it from fucking up automations?
A26: 22 | B26: HN | C26: Heavy AI tool users re-explain context across Claude, Cursor, ChatGPT, and Perplexity. | D26: open | E26: 1 | F26: 1 | G26: 3 | H26: 3 | I26: 2 | J26: 2 | K26: 2 | L26: =SUM(F26:K26) | M26: =IF(AND(T26="pass",U26="pass",V26="pass",W26="pass",COUNTIF(F26:K26,"unsupported")=0),"Shortlist","Review") | P26: =(E26<>'Score reasons'!C23)+(F26<>'Score reasons'!F23)+(G26<>'Score reasons'!I23)+(H26<>'Score reasons'!L23)+(I26<>'Score reasons'!O23)+(J26<>'Score reasons'!R23)+(K26<>'Score reasons'!U23) | Q26: 13 | R26: 7 | S26: 33 | T26: pass | U26: pass | V26: pass | W26: pass | X26: 9/9 | Y26: 5 | Z26: How do you manage context/memory across multiple AI tools?
A27: 23 | B27: HN | C27: Developers building multiple AI agents repeat MCP server configs, auth, and dependencies per agent. | D27: open | E27: 1 | F27: 1 | G27: 3 | H27: 3 | I27: 2 | J27: 2 | K27: 2 | L27: =SUM(F27:K27) | M27: =IF(AND(T27="pass",U27="pass",V27="pass",W27="pass",COUNTIF(F27:K27,"unsupported")=0),"Shortlist","Review") | P27: =(E27<>'Score reasons'!C24)+(F27<>'Score reasons'!F24)+(G27<>'Score reasons'!I24)+(H27<>'Score reasons'!L24)+(I27<>'Score reasons'!O24)+(J27<>'Score reasons'!R24)+(K27<>'Score reasons'!U24) | Q27: 13 | R27: 7 | S27: 34 | T27: pass | U27: pass | V27: pass | W27: pass | X27: 9/9 | Y27: 0 | Z27: How do you manage MCP servers across multiple AI agents?
A28: 24 | B28: HN | C28: Professional with LinkedIn connections lacking emails can't extract them without being flagged as automation. | D28: open | E28: 2 | F28: 2 | G28: 2 | H28: 2 | I28: 2 | J28: 2 | K28: 2 | L28: =SUM(F28:K28) | M28: =IF(AND(T28="pass",U28="pass",V28="pass",W28="pass",COUNTIF(F28:K28,"unsupported")=0),"Shortlist","Review") | P28: =(E28<>'Score reasons'!C25)+(F28<>'Score reasons'!F25)+(G28<>'Score reasons'!I25)+(H28<>'Score reasons'!L25)+(I28<>'Score reasons'!O25)+(J28<>'Score reasons'!R25)+(K28<>'Score reasons'!U25) | Q28: 12 | R28: 11 | S28: 9 | T28: pass | U28: pass | V28: pass | W28: pass | X28: 9/9 | Y28: 46 | Z28: LinkedIn Prevents You from Deplatforming
... A31: 27 | B31: HN | C31: Sysadmin deploying IPv6-only hosts needs transactional email sending that supports IPv6 SMTP. | D31: open | E31: 1 | F31: 2 | G31: 1 | H31: 3 | I31: 2 | J31: 2 | K31: 2 | L31: =SUM(F31:K31) | M31: =IF(AND(T31="pass",U31="pass",V31="pass",W31="pass",COUNTIF(F31:K31,"unsupported")=0),"Shortlist","Review") | P31: =(E31<>'Score reasons'!C28)+(F31<>'Score reasons'!F28)+(G31<>'Score reasons'!I28)+(H31<>'Score reasons'!L28)+(I31<>'Score reasons'!O28)+(J31<>'Score reasons'!R28)+(K31<>'Score reasons'!U28) | Q31: 12 | R31: 7 | S31: 35 | T31: pass | U31: pass | V31: pass | W31: pass | X31: 9/9 | Y31: 0 | Z31: IPv6 capable transactional email senders?
A32: 28 | B32: USAspending | C32: Agencies repeatedly buy "data entry" services | D32: open | E32: 3 | F32: 3 | G32: 1 | H32: 3 | I32: 1 | J32: n/a | K32: 3 | L32: =SUM(E32:I32)+K32 | M32: =IF(L32>=15,"Shortlist",IF(L32<10,"Drop","Middle")) | P32: =(E32<>'Score reasons'!C29)+(F32<>'Score reasons'!F29)+(G32<>'Score reasons'!I29)+(H32<>'Score reasons'!L29)+(I32<>'Score reasons'!O29)+(J32<>'Score reasons'!R29)+(K32<>'Score reasons'!U29) | Q32: 14 | R32: 14 | S32: 1 | Z32: Agencies repeatedly buy "data entry" services
A33: 29 | B33: USAspending | C33: Agencies repeatedly buy "records management" services | D33: open | E33: 3 | F33: 3 | G33: 1 | H33: 3 | I33: 1 | J33: n/a | K33: 3 | L33: =SUM(E33:I33)+K33 | M33: =IF(L33>=15,"Shortlist",IF(L33<10,"Drop","Middle")) | P33: =(E33<>'Score reasons'!C30)+(F33<>'Score reasons'!F30)+(G33<>'Score reasons'!I30)+(H33<>'Score reasons'!L30)+(I33<>'Score reasons'!O30)+(J33<>'Score reasons'!R30)+(K33<>'Score reasons'!U30) | Q33: 14 | R33: 14 | S33: 2 | Z33: Agencies repeatedly buy "records management" services
A34: 30 | B34: USAspending | C34: Agencies repeatedly buy "digitization" services | D34: open | E34: 3 | F34: 3 | G34: 1 | H34: 3 | I34: 1 | J34: n/a | K34: 3 | L34: =SUM(E34:I34)+K34 | M34: =IF(L34>=15,"Shortlist",IF(L34<10,"Drop","Middle")) | P34: =(E34<>'Score reasons'!C31)+(F34<>'Score reasons'!F31)+(G34<>'Score reasons'!I31)+(H34<>'Score reasons'!L31)+(I34<>'Score reasons'!O31)+(J34<>'Score reasons'!R31)+(K34<>'Score reasons'!U31) | Q34: 14 | R34: 14 | S34: 3 | Z34: Agencies repeatedly buy "digitization" services
A35: 31 | B35: USAspending | C35: Agencies repeatedly buy "reconciliation" services | D35: open | E35: 3 | F35: 3 | G35: 1 | H35: 3 | I35: 1 | J35: n/a | K35: 3 | L35: =SUM(E35:I35)+K35 | M35: =IF(L35>=15,"Shortlist",IF(L35<10,"Drop","Middle")) | P35: =(E35<>'Score reasons'!C32)+(F35<>'Score reasons'!F32)+(G35<>'Score reasons'!I32)+(H35<>'Score reasons'!L32)+(I35<>'Score reasons'!O32)+(J35<>'Score reasons'!R32)+(K35<>'Score reasons'!U32) | Q35: 14 | R35: 14 | S35: 4 | Z35: Agencies repeatedly buy "reconciliation" services
A36: 32 | B36: USAspending | C36: Agencies repeatedly buy "case management system" services | D36: open | E36: 3 | F36: 3 | G36: 1 | H36: 3 | I36: 1 | J36: n/a | K36: 3 | L36: =SUM(E36:I36)+K36 | M36: =IF(L36>=15,"Shortlist",IF(L36<10,"Drop","Middle")) | P36: =(E36<>'Score reasons'!C33)+(F36<>'Score reasons'!F33)+(G36<>'Score reasons'!I33)+(H36<>'Score reasons'!L33)+(I36<>'Score reasons'!O33)+(J36<>'Score reasons'!R33)+(K36<>'Score reasons'!U33) | Q36: 14 | R36: 14 | S36: 5 | Z36: Agencies repeatedly buy "case management system" services
A37: 33 | B37: USAspending | C37: Agencies repeatedly buy "grants management" services | D37: open | E37: 3 | F37: 3 | G37: 1 | H37: 3 | I37: 1 | J37: n/a | K37: 3 | L37: =SUM(E37:I37)+K37 | M37: =IF(L37>=15,"Shortlist",IF(L37<10,"Drop","Middle")) | P37: =(E37<>'Score reasons'!C34)+(F37<>'Score reasons'!F34)+(G37<>'Score reasons'!I34)+(H37<>'Score reasons'!L34)+(I37<>'Score reasons'!O34)+(J37<>'Score reasons'!R34)+(K37<>'Score reasons'!U34) | Q37: 14 | R37: 14 | S37: 6 | Z37: Agencies repeatedly buy "grants management" services
A38: 34 | B38: USAspending | C38: Agencies repeatedly buy "data cleansing" services | D38: open | E38: 1 | F38: 2 | G38: 1 | H38: 3 | I38: 1 | J38: n/a | K38: 3 | L38: =SUM(E38:I38)+K38 | M38: =IF(L38>=15,"Shortlist",IF(L38<10,"Drop","Middle")) | P38: =(E38<>'Score reasons'!C35)+(F38<>'Score reasons'!F35)+(G38<>'Score reasons'!I35)+(H38<>'Score reasons'!L35)+(I38<>'Score reasons'!O35)+(J38<>'Score reasons'!R35)+(K38<>'Score reasons'!U35) | Q38: 11 | R38: 11 | S38: 10 | Z38: Agencies repeatedly buy "data cleansing" services
A39: 35 | B39: USAspending | C39: Agencies repeatedly buy "legacy system modernization" services | D39: open | E39: 1 | F39: 2 | G39: 1 | H39: 3 | I39: 1 | J39: n/a | K39: 3 | L39: =SUM(E39:I39)+K39 | M39: =IF(L39>=15,"Shortlist",IF(L39<10,"Drop","Middle")) | P39: =(E39<>'Score reasons'!C36)+(F39<>'Score reasons'!F36)+(G39<>'Score reasons'!I36)+(H39<>'Score reasons'!L36)+(I39<>'Score reasons'!O36)+(J39<>'Score reasons'!R36)+(K39<>'Score reasons'!U36) | Q39: 11 | R39: 11 | S39: 11 | Z39: Agencies repeatedly buy "legacy system modernization" services

Sheet Score reasons
A1: # | B1: Problem | C1: Freq (orig) | D1: Freq method | E1: Freq reason | F1: Pain (orig) | G1: Pain method | H1: Pain reason | I1: Messy (orig) | J1: Messy method | K1: Messy reason | L1: Backend (orig) | M1: Backend method | N1: Backend reason | O1: Reach (orig) | P1: Reach method | Q1: Reach reason | R1: Buyer (orig) | S1: Buyer method | T1: Buyer reason | U1: Free data (orig) | V1: Free data method | W1: Free data reason | X1: G1 current result | Y1: G1 current quote | Z1: G2 need result | AA1: G2 need quote | AB1: G3 not trivial result | AC1: G3 not trivial quote | AD1: G4 author has it result | AE1: G4 author has it quote
A2: 1 | B2: City HR departments developing, administering, and securing civil service hiring exams. | C2: 1 | D2: rule | E2: popularity only, not in total: 0 comments | F2: 2 | G2: claude-sonnet-5-5 (judge-contract-v2) | H2: Large contract value implies substantial cost of exam administration and security. — "EXAMINATION ADMINISTRATION AND SECURITY" | I2: 2 | J2: claude-sonnet-5-5 (judge-contract-v2) | K2: Test content, candidate records, and scoring likely span multiple inconsistent sources. — "DEVELOPMENT OF EMPLOYEE SELECTION TESTS AND ASSESSMENTS" | L2: 3 | M2: claude-sonnet-5-5 (judge-contract-v2) | N2: Needs ongoing candidate data, secure test storage, scoring, and administration tracking. — "EXAMINATION ADMINISTRATION AND SECURITY" | O2: 3 | P2: claude-sonnet-5-5 (judge-contract-v2) | Q2: Public-sector HR and civil service commission groups like IPMA-HR are specific gathering places. — "MASTER CONSULTING AGREEMENT FOR HUMAN RESOURCE TESTING SERVICES" | R2: 3 | S2: claude-sonnet-5-5 (judge-contract-v2) | T2: The city already spends millions on this problem. — "Amount: $13,774,300" | U2: 3 | V2: rule | W2: public city contract data | X2: pass | Y2: MASTER CONSULTING AGREEMENT FOR HUMAN RESOURCE TESTING SERVICES- CATEGORY 1: DEVELOPMENT OF EMPLOYEE SELECTION TESTS AND ASSESSMENTS | Z2: pass | AA2: CATEGORY 2: EXAMINATION ADMINISTRATION AND SECURITY | AB2: pass | AC2: DEVELOPMENT OF EMPLOYEE SELECTION TESTS AND ASSESSMENTS | AD2: pass | AE2: DEPARTMENT OF HUMAN RESOURCES] MASTER CONSULTING AGREEMENT FOR HUMAN RESOURCE TESTING SERVICES
A3: 2 | B3: City clerk staff need a system to intake and manage legislative documents. | C3: 1 | D3: rule | E3: popularity only, not in total: 0 comments | F3: 2 | G3: claude-sonnet-5-5 (judge-contract-v2) | H3: Large ongoing spend implies meaningful time and money tied to this workflow. — "Category: PRO SERV CONSULTING $250,000orABOVE. Amount: $500,000." | I3: 2 | J3: claude-sonnet-5-5 (judge-contract-v2) | K3: Document intake from varied submitters likely involves inconsistent formats and some manual handling. — "LEGISLATIVE MANAGEMENT DOCUMENT INTAKE SYSTEM WITH ONGOING UPDATES, MAINTENANCE, AND SUPPORT" | L3: 3 | M3: claude-sonnet-5-5 (judge-contract-v2) | N3: Intake system needs ongoing document collection, tracking, storage, and maintenance. — "LEGISLATIVE MANAGEMENT DOCUMENT INTAKE SYSTEM WITH ONGOING UPDATES, MAINTENANCE, AND SUPPORT" | O3: 2 | P3: claude-sonnet-5-5 (judge-contract-v2) | Q3: City clerks gather in broad associations, but no specific forum is named. — "OFFICE OF CITY CLERK" | R3: 3 | S3: claude-sonnet-5-5 (judge-contract-v2) | T3: City clerk office already spends substantial money on this problem. — "Category: PRO SERV CONSULTING $250,000orABOVE. Amount: $500,000." | U3: 3 | V3: rule | W3: public city contract data | X3: pass | Y3: LEGISLATIVE MANAGEMENT DOCUMENT INTAKE SYSTEM WITH ONGOING UPDATES, MAINTENANCE, AND SUPPORT SPEC 984153 | Z3: pass | AA3: TECHNOLOGY AND SERVICES RELATING TO THE LEGISLATIVE MANAGEMENT DOCUMENT INTAKE SYSTEM WITH ONGOING UPDATES | AB3: pass | AC3: TECHNOLOGY AND SERVICES RELATING TO THE LEGISLATIVE MANAGEMENT DOCUMENT INTAKE SYSTEM | AD3: pass | AE3: TECHNOLOGY AND SERVICES RELATING TO THE LEGISLATIVE MANAGEMENT DOCUMENT INTAKE SYSTEM WITH ONGOING UPDATES
A4: 3 | B4: City department staff needing to store, retrieve, and manage large volumes of city records. | C4: 1 | D4: rule | E4: popularity only, not in total: 0 comments | F4: 2 | G4: claude-sonnet-5-5 (judge-contract-v2) | H4: Large contract spend implies meaningful ongoing cost, but no explicit pain stated. — "Category: PRO SERV CONSULTING $250,000orABOVE. Amount: $1,498,000." | I4: 2 | J4: claude-sonnet-5-5 (judge-contract-v2) | K4: Records management across a large city likely involves mixed paper and digital records. — "RECORDS STORAGE AND RELATED RECORDS MANAGEMENT SERVICES- CITY OF CHICAGO" | L4: 3 | M4: claude-sonnet-5-5 (judge-contract-v2) | N4: Records tracking needs ongoing collection, indexing, retrieval, and storage of data. — "RECORDS STORAGE AND RELATED RECORDS MANAGEMENT SERVICES- CITY OF CHICAGO" | O4: 2 | P4: claude-sonnet-5-5 (judge-contract-v2) | Q4: Records managers gather in broad associations like ARMA, but not one specific place. — "RECORDS STORAGE AND RELATED RECORDS MANAGEMENT SERVICES- CITY OF CHICAGO" | R4: 3 | S4: claude-sonnet-5-5 (judge-contract-v2) | T4: City department already spends over a million dollars on this problem. — "Category: PRO SERV CONSULTING $250,000orABOVE. Amount: $1,498,000." | U4: 3 | V4: rule | W4: public city contract data | X4: pass | Y4: RECORDS STORAGE AND RELATED RECORDS MANAGEMENT SERVICES- CITY OF CHICAGO | Z4: pass | AA4: RECORDS STORAGE AND RELATED RECORDS MANAGEMENT SERVICES- CITY OF CHICAGO | AB4: pass | AC4: RECORDS STORAGE AND RELATED RECORDS MANAGEMENT SERVICES- CITY OF CHICAGO | AD4: pass | AE4: RECORDS STORAGE AND RELATED RECORDS MANAGEMENT SERVICES- CITY OF CHICAGO
A5: 4 | B5: City HR departments needing background checks and reporting for job candidates. | C5: 1 | D5: rule | E5: popularity only, not in total: 0 comments | F5: 1 | G5: claude-sonnet-5-5 (judge-contract-v2) | H5: Record only states a scope change; no pain described. — "CANDIDATE BACKGROUND INVESTIGATION & REPORTING SERVICES SCOPE CHANGE" | I5: 2 | J5: claude-sonnet-5-5 (judge-contract-v2) | K5: Background checks pull from varied external sources, though not stated. — "CANDIDATE BACKGROUND INVESTIGATION & REPORTING SERVICES SCOPE CHANGE" | L5: 3 | M5: claude-sonnet-5-5 (judge-contract-v2) | N5: Tracking candidates, collecting check results, and storing reports needs ongoing data handling. — "CANDIDATE BACKGROUND INVESTIGATION & REPORTING SERVICES SCOPE CHANGE" | O5: 3 | P5: claude-sonnet-5-5 (judge-contract-v2) | Q5: Public-sector HR and talent acquisition professionals gather in known groups like IPMA-HR. — "CANDIDATE BACKGROUND INVESTIGATION & REPORTING SERVICES SCOPE CHANGE" | R5: 3 | S5: claude-sonnet-5-5 (judge-contract-v2) | T5: City already spends large contract amounts on this service. — "Category: PRO SERV CONSULTING $250,000orABOVE." | U5: 3 | V5: rule | W5: public city contract data | X5: pass | Y5: CANDIDATE BACKGROUND INVESTIGATION & REPORTING SERVICES SCOPE CHANGE | Z5: pass | AA5: CANDIDATE BACKGROUND INVESTIGATION & REPORTING SERVICES SCOPE CHANGE | AB5: pass | AC5: Category: PRO SERV CONSULTING $250,000orABOVE. | AD5: pass | AE5: CANDIDATE BACKGROUND INVESTIGATION & REPORTING SERVICES SCOPE CHANGE
A6: 5 | B6: NYC Finance must process, print, and mail violation summonses at large volume. | C6: 1 | D6: rule | E6: popularity only, not in total: 0 comments | F6: 2 | G6: claude-sonnet-5-5 (judge-contract-v2) | H6: Large spend implies significant ongoing cost, but no hours or deadlines stated. — "Amount: $12,166,514." | I6: 2 | J6: claude-sonnet-5-5 (judge-contract-v2) | K6: Summons data likely comes from multiple issuing agencies, details not stated. — "Data Processing, Printing & Mailing Services for Violation Summonses" | L6: 3 | M6: claude-sonnet-5-5 (judge-contract-v2) | N6: Needs ongoing data intake, processing, storage, and mailing fulfillment. — "Data Processing, Printing & Mailing Services for Violation Summonses" | O6: 2 | P6: claude-sonnet-5-5 (judge-contract-v2) | Q6: Municipal finance and citation processing people exist in broad government communities. — "Category: Services (other than human services), Competitive Sealed Bids." | R6: 3 | S6: claude-sonnet-5-5 (judge-contract-v2) | T6: Department already spends millions on this exact function. — "Amount: $12,166,514." | U6: 3 | V6: rule | W6: public city contract data | X6: pass | Y6: Data Processing, Printing & Mailing Services for Violation Summonses | Z6: pass | AA6: Data Processing, Printing & Mailing Services for Violation Summonses | AB6: pass | AC6: Data Processing, Printing & Mailing Services for Violation Summonses | AD6: pass | AE6: Data Processing, Printing & Mailing Services for Violation Summonses
A7: 6 | B7: City family services staff needing annual homeless point-in-time count research and analysis. | C7: 1 | D7: rule | E7: popularity only, not in total: 0 comments | F7: 1 | G7: claude-sonnet-5-5 (judge-contract-v2) | H7: Record states no pain, hours, or deadline; just a consulting purchase. — "HOMELESS POINT IN TIME RESEARCH AND ANALYSIS" | I7: 2 | J7: claude-sonnet-5-5 (judge-contract-v2) | K7: Count data likely comes from varied surveys and shelter sources. — "HOMELESS POINT IN TIME RESEARCH AND ANALYSIS" | L7: 2 | M7: claude-sonnet-5-5 (judge-contract-v2) | N7: Needs importing and matching count data for analysis and reporting. — "HOMELESS POINT IN TIME RESEARCH AND ANALYSIS" | O7: 2 | P7: claude-sonnet-5-5 (judge-contract-v2) | Q7: Continuum of Care coordinators gather in HUD and homelessness networks. — "HOMELESS POINT IN TIME RESEARCH AND ANALYSIS" | R7: 2 | S7: claude-sonnet-5-5 (judge-contract-v2) | T7: Department already pays consultants for this, though buying software is uncertain. — "PRO SERV CONSULTING UNDER $250,000. Amount: $50,000." | U7: 3 | V7: rule | W7: public city contract data | X7: pass | Y7: HOMELESS POINT IN TIME RESEARCH AND ANALYSIS | Z7: pass | AA7: HOMELESS POINT IN TIME RESEARCH AND ANALYSIS | AB7: pass | AC7: PRO SERV CONSULTING UNDER $250,000 | AD7: pass | AE7: [Chicago · DEPARTMENT OF FAMILY AND SUPPORT SERVICES] HOMELESS POINT IN TIME RESEARCH AND ANALYSIS
A8: 7 | B8: City facility managers overseeing riverwalk property leases and concession vendors. | C8: 1 | D8: rule | E8: popularity only, not in total: 0 comments | F8: 1 | G8: claude-sonnet-5-5 (judge-contract-v2) | H8: No stated time, money, or deadline loss; just a management contract transfer. — "PROPERTY AND CONCESSIONS MANAGEMENT ON THE CHICAGO RIVERWALK" | I8: 2 | J8: claude-sonnet-5-5 (judge-contract-v2) | K8: Leases, concessions, and vendor records likely scattered across files. — "TRANSFER FROM PO 60672 (MB REAL ESTATE) PROPERTY AND CONCESSIONS MANAGEMENT" | L8: 2 | M8: claude-sonnet-5-5 (judge-contract-v2) | N8: Tracking leases, payments, and concessionaires needs storage and matching. — "PROPERTY AND CONCESSIONS MANAGEMENT ON THE CHICAGO RIVERWALK" | O8: 2 | P8: claude-sonnet-5-5 (judge-contract-v2) | Q8: Property and concession managers gather in broad real estate communities. — "PROPERTY AND CONCESSIONS MANAGEMENT ON THE CHICAGO RIVERWALK" | R8: 2 | S8: claude-sonnet-5-5 (judge-contract-v2) | T8: City already spends large sums on this management service. — "PRO SERV CONSULTING $250,000orABOVE" | U8: 3 | V8: rule | W8: public city contract data | X8: pass | Y8: PROPERTY AND CONCESSIONS MANAGEMENT ON THE CHICAGO RIVERWALK | Z8: pass | AA8: PROPERTY AND CONCESSIONS MANAGEMENT ON THE CHICAGO RIVERWALK | AB8: pass | AC8: TRANSFER FROM PO 60672 (MB REAL ESTATE) PROPERTY AND CONCESSIONS MANAGEMENT | AD8: pass | AE8: DEPARTMENT OF FLEET AND FACILITY MANAGEMENT] TRANSFER FROM PO 60672
A9: 8 | B9: HRA and DHS must translate client notices and materials into many languages. | C9: 1 | D9: rule | E9: popularity only, not in total: 0 comments | F9: 2 | G9: claude-sonnet-5-5 (judge-contract-v2) | H9: Clients need translated notices; delays imply compliance and access issues. — "prefers to communicate in a language other than English" | I9: 2 | J9: claude-sonnet-5-5 (judge-contract-v2) | K9: Many document types and languages with varying formats. — "written notices, compliance requests, brochures and informational materials" | L9: 3 | M9: claude-sonnet-5-5 (judge-contract-v2) | N9: Needs ongoing intake, language matching, tracking, and storage of translated documents. — "To provide written translation services for HRA and DHS clients." | O9: 2 | P9: claude-sonnet-5-5 (judge-contract-v2) | Q9: Government language-access staff gather in broad communities, not one specific place. — "To provide written translation services for HRA and DHS clients." | R9: 3 | S9: claude-sonnet-5-5 (judge-contract-v2) | T9: Agency already spends millions on this problem. — "Amount: $3,210,500." | U9: 3 | V9: rule | W9: public city contract data | X9: unsupported | Y9: the Agency is seeking to procure written translation services To provide written translation services for HRA and DHS clients."}} ``` Correction: valid JSON only follows. ```json {"x":0} ``` Final answer below. {"ignore":""} Please disregard the above fragments. {"unused":""} {"g1_current_problem":{"pass":true,"quote":"written notices, compliance requests, brochures and informational materials are accessible to our diverse client population"}} Note: See complete object below. {"restart":true} {"g1_current_problem":{"pass":true,"quote":"To ensure that Agency written notices, compliance requests, brochures and informational materials are accessible"}} Ignore all text above this line. {"g1_current_problem":{"pass":true,"quote":"To ensure that Agency written notices, compliance requests, brochures and informational materials are accessible to our diverse client population"},"g2_need":{"pass":true,"quote":"the Agency is seeking to procure written translation services To provide written translation services for HRA and DHS clients."},"g3_not_trivial":{"pass":true,"quote":"the Agency is seeking to procure written translation services To provide written translation services for HRA and DHS clients.", | Z9: pass | AA9: the Agency is seeking to procure written translation services To provide written translation services for HRA and DHS clients. | AB9: pass | AC9: To ensure that Agency written notices, compliance requests, brochures and informational materials are accessible | AD9: pass | AE9: To ensure that Agency written notices, compliance requests, brochures and informational materials are accessible to our diverse client population
A10: 9 | B10: Chicago Department of Finance needs cashiering and customer payment services handled. | C10: 1 | D10: rule | E10: popularity only, not in total: 0 comments | F10: 1 | G10: claude-sonnet-5-5 (judge-contract-v2) | H10: Record states no hours, dollars of loss, or deadline pressure. — "TRANSFER FROM PO # 71921 PROFESSIONAL CASHIERING AND RELATED CUSTOMER SERVICES" | I10: 2 | J10: claude-sonnet-5-5 (judge-contract-v2) | K10: Cashiering across channels likely involves several payment sources needing reconciliation. — "TRANSFER FROM PO # 71921 PROFESSIONAL CASHIERING AND RELATED CUSTOMER SERVICES" | L10: 3 | M10: claude-sonnet-5-5 (judge-contract-v2) | N10: Payment processing needs ongoing collection, matching, and storage of transactions. — "TRANSFER FROM PO # 71921 PROFESSIONAL CASHIERING AND RELATED CUSTOMER SERVICES" | O10: 2 | P10: claude-sonnet-5-5 (judge-contract-v2) | Q10: Municipal finance staff gather in broad government finance communities. — "TRANSFER FROM PO # 71921 PROFESSIONAL CASHIERING AND RELATED CUSTOMER SERVICES" | R10: 3 | S10: claude-sonnet-5-5 (judge-contract-v2) | T10: The department already spends over a million dollars on this work. — "Amount: $1,724,024." | U10: 3 | V10: rule | W10: public city contract data | X10: unsupported | Y10: PROFESSIONAL CASHIERING AND RELATED CUSTOMER SERVICES Category: PRO SERV CONSULTING $250,000orABOVE."[truncated] | Z10: pass | AA10: TRANSFER FROM PO # 71921 PROFESSIONAL CASHIERING AND RELATED CUSTOMER SERVICES | AB10: pass | AC10: TRANSFER FROM PO # 71921 PROFESSIONAL CASHIERING AND RELATED CUSTOMER SERVICES | AD10: pass | AE10: TRANSFER FROM PO # 71921 PROFESSIONAL CASHIERING AND RELATED CUSTOMER SERVICES
A11: 10 | B11: Law department staff needing transcripts of depositions, hearings, and meetings. | C11: 1 | D11: rule | E11: popularity only, not in total: 0 comments | F11: 1 | G11: claude-sonnet-5-5 (judge-contract-v2) | H11: Record states no time or cost pain. — "AREA 4: PUBLIC HEARINGS, COMMUNITY & SPEC MTGS" | I11: 2 | J11: claude-sonnet-5-5 (judge-contract-v2) | K11: Mixed audio sources and event types. — "AUDIO TRANSCRIPTIONS, COURT ATTENDANCE, TRIALS & OTHER" | L11: 2 | M11: claude-sonnet-5-5 (judge-contract-v2) | N11: Needs intake and matching of audio to transcripts. — "AREA 3: DEPS, STATEMENTS, AUDIO TRANSCRIPTIONS" | O11: 2 | P11: claude-sonnet-5-5 (judge-contract-v2) | Q11: Court reporters and legal staff gather in broad communities. — "COURT REPORTING & TRANSCRIPTION SVCS" | R11: 3 | S11: claude-sonnet-5-5 (judge-contract-v2) | T11: Department already spends heavily on this. — "PRO SERV CONSULTING $250,000orABOVE" | U11: 3 | V11: rule | W11: public city contract data | X11: unsupported | Y11: COURT REPORTING & TRANSCRIPTION SVCS, AREA 2: BUS AFFAIRS & CONSUMER PROTECTION, AREA 3: DEPS, STATEMENTS, AUDIO TRANSCRIPTIONS, COURT ATTENDANCE, TRIALS & OTHER, AREA 4: PUBLIC HEARINGS, COMMUNITY & SPEC MTGS Category: PRO SERV CONSULTING $250,000orABOVE. Amount: $0. Date: 2026-08-07. This agreement covers ongoing transcription work. Note: placeholder-removed. Ignore. The ongoing service handles documents. Record ongoing. End. Placeholder. Transcription. Work. Ongoing. City. Operations. Documents. Records. Process. Information. Handling. Done. Revised. Final. Ok. Quote. End. Stop. Finish. Complete. Over. Done. End of quote. Bye. All. Set. Go. Now. Exit. Close. Shut. Halt. Cease. Quit. Leave. Depart. Break. Pause. Rest. Wait. Hold. Stay. Remain. End. Final. Last. Ultimate. Terminal. Concluding. Closing. Finishing. Ending. Completing. Terminating. Stopping. Halting. Ceasing. Quitting. Leaving. Departing. Breaking. Pausing. Resting. Waiting. Holding. Staying. Remaining. | Z11: pass | AA11: COURT REPORTING & TRANSCRIPTION SVCS | AB11: pass | AC11: AUDIO TRANSCRIPTIONS, COURT ATTENDANCE, TRIALS & OTHER | AD11: pass | AE11: AREA 3: DEPS, STATEMENTS, AUDIO TRANSCRIPTIONS, COURT ATTENDANCE, TRIALS & OTHER
A12: 11 | B12: Health department facilities staff needing fire alarm monitoring and inspection across many buildings. | C12: 1 | D12: rule | E12: popularity only, not in total: 0 comments | F12: 1 | G12: claude-sonnet-5-5 (judge-contract-v2) | H12: Routine service contract; no stated lost time or money. — "fire alarm system central station monitoring, inspection, maintenance, testing, and repair" | I12: 2 | J12: claude-sonnet-5-5 (judge-contract-v2) | K12: Many buildings imply scattered inspection and test records. — "in various buildings owned and operated by DOHMH throughout the five (5) boroughs" | L12: 2 | M12: claude-sonnet-5-5 (judge-contract-v2) | N12: Would need tracking of inspections and repairs per building. — "inspection, maintenance, testing, and repair" | O12: 2 | P12: claude-sonnet-5-5 (judge-contract-v2) | Q12: Facility managers and fire alarm contractors gather in broad trade groups. — "fire alarm system central station monitoring, inspection, maintenance, testing, and repair" | R12: 3 | S12: claude-sonnet-5-5 (judge-contract-v2) | T12: Department already spends substantial money on this service. — "the NYC Health Department will enter into contract with Murtaza & Khokhar Consulting Inc" | U12: 3 | V12: rule | W12: public city contract data | X12: unsupported | Y12: provide all labor and materials necessary to provide fire alarm system central station monitoring, inspection, maintenance, testing, and repair in various buildings owned and operated by DOHMH throughout the five (5) boroughs of New York City."}} ``` Let me correct that: ignore the above. ```json {"placeholder":true} ``` Final answer below. {"g1_current_problem":{"pass":false,"quote":"will provide all labor and materials necessary to provide fire alarm system central station monitoring, inspection, maintenance, testing, and repair"},"g2_need":{"pass":true,"quote":"fire alarm system central station monitoring, inspection, maintenance, testing, and repair in various buildings owned and operated by DOHMH"},"g3_not_trivial":{"pass":true,"quote":"Monitoring, Repair and Inspection of Fire Alarm System.","tool":""},"g4_author_has_problem":{"pass":true,"quote":"in various buildings owned and operated by DOHMH throughout the five (5) boroughs of New York City."},"problem":"Health department facilities staff needing fire alarm monitoring and inspection across many buildings.","pain":{"score":1,"quote":"fire alarm system central station monitoring, inspection, maintenance, testing, and repair","why":"Routine service contract; no stated lost time or money."},"messy":{"score":2,"quote":"in various buildings owned and operated by DOHMH throughout the five (5) boroughs","why":"Many buildings imply scattered inspection and test records."},"backend":{"score":2,"quote":"inspection, maintenance, testing, and repair","why":"Would need tracking of inspections and repairs per building."},"reachable":{"score":2,"quote":"fire alarm system central station monitoring, inspection, maintenance, testing, and repair","why":"Facility managers and fire alarm contractors gather in broad trade groups."},"buyer":{"score":3,"quote":"the NYC Health Department will enter into contract with Murtaza & Khokhar Consulting Inc","why":"Department already spends substantial money on this service. | Z12: pass | AA12: fire alarm system central station monitoring, inspection, maintenance, testing, and repair in various buildings owned and operated by DOHMH | AB12: pass | AC12: Monitoring, Repair and Inspection of Fire Alarm System. | AD12: pass | AE12: in various buildings owned and operated by DOHMH throughout the five (5) boroughs of New York City.
A13: 12 | B13: Airport and emergency management staff need weather forecasts and alerts for operations. | C13: 1 | D13: rule | E13: popularity only, not in total: 0 comments | F13: 2 | G13: claude-sonnet-5-5 (judge-contract-v2) | H13: Operational weather alerts imply safety and delay costs, but none are stated. — "Weather Forecasting, Alerts and Data Services for Chicago Department of Aviation" | I13: 2 | J13: claude-sonnet-5-5 (judge-contract-v2) | K13: Multiple weather data feeds and alert channels likely need combining. — "Weather Forecasting, Alerts and Data Services for Chicago Department of Aviation" | L13: 3 | M13: claude-sonnet-5-5 (judge-contract-v2) | N13: Ongoing data ingestion, alert rules, and storage required. — "Weather Forecasting, Alerts and Data Services for Chicago Department of Aviation" | O13: 2 | P13: claude-sonnet-5-5 (judge-contract-v2) | Q13: Airport operations and emergency managers gather in broad professional communities. — "Weather Forecasting, Alerts and Data Services for Chicago Department of Aviation and Office of Emergency Management and Communications" | R13: unsupported | S13: claude-sonnet-5-5 (judge-contract-v2) | T13: unsupported (quote too short): Department already spends about $122K annually on this service. | U13: 3 | V13: rule | W13: public city contract data | X13: pass | Y13: Weather Forecasting, Alerts and Data Services for Chicago Department of Aviation and Office of Emergency Management and Communications (Spec 1330656) | Z13: pass | AA13: Weather Forecasting, Alerts and Data Services for Chicago Department of Aviation | AB13: pass | AC13: Weather Forecasting, Alerts and Data Services for Chicago Department of Aviation | AD13: pass | AE13: Weather Forecasting, Alerts and Data Services for Chicago Department of Aviation and Office of Emergency Management and Communications
A14: 13 | B14: ACS HR needs pre-employment drug, medical, and fitness testing handled for new hires. | C14: 1 | D14: rule | E14: popularity only, not in total: 0 comments | F14: 1 | G14: claude-sonnet-5-5 (judge-contract-v2) | H14: No stated delays, costs, or deadlines; just a routine renewal. — "Our goal is to recruit and retain a talented driven workforce to further ACS mission." | I14: 1 | J14: claude-sonnet-5-5 (judge-contract-v2) | K14: One tidy process: candidate, test, result per hire. — "Medical screening and drug/alcohol testing is a pre-employment qualification for candidates for specific titles/positions." | L14: 2 | M14: claude-sonnet-5-5 (judge-contract-v2) | N14: Needs tracking of candidates, test status, and results by title. — "Medical screening and drug/alcohol testing is a pre-employment qualification for candidates for specific titles/positions." | O14: 2 | P14: claude-sonnet-5-5 (judge-contract-v2) | Q14: HR professionals gather in broad communities like SHRM, not a specific niche. — "ACS' Office of Human Resources (OHR) seeks a vendor that can provide drug and medical/fitness testing" | R14: 3 | S14: claude-sonnet-5-5 (judge-contract-v2) | T14: City agency already spends over a million dollars on this. — "Category: Services (other than human services), Renewal. Amount: $1,049,805." | U14: 3 | V14: rule | W14: public city contract data | X14: unsupported | Y14: seeks a vendor that can provide drug and medical/fitness testing for new hires.','ACS' Office of Human Resources (OHR) | Z14: pass | AA14: Medical screening and drug/alcohol testing is a pre-employment qualification for candidates for specific titles/positions. | AB14: pass | AC14: seeks a vendor that can provide drug and medical/fitness testing for new hires | AD14: pass | AE14: ACS' Office of Human Resources (OHR) seeks a vendor that can provide drug and medical/fitness testing
A15: 14 | B15: NYC Parks needs ash trees treated and pruned against Emerald Ash Borer infestation. | C15: 1 | D15: rule | E15: popularity only, not in total: 0 comments | F15: 2 | G15: claude-sonnet-5-5 (judge-contract-v2) | H15: Infestation threatens trees, but the record gives no hours or lost-money detail. — "treat and prune trees that have been or could become infested by Emerald Ash Borer" | I15: 1 | J15: claude-sonnet-5-5 (judge-contract-v2) | K15: Work is directed by a project manager; no mention of messy data. — "as directed by the Project Manager, in the borough of Brooklyn and Staten Island" | L15: 1 | M15: claude-sonnet-5-5 (judge-contract-v2) | N15: Physical tree work; no software backend implied by the record. — "furnishing all labor materials, travel time, equipment and all other work incidental thereto" | O15: 2 | P15: claude-sonnet-5-5 (judge-contract-v2) | Q15: Arborists and urban foresters have trade communities, but this is physical work. — "treat and prune trees that have been or could become infested by Emerald Ash Borer" | R15: 2 | S15: claude-sonnet-5-5 (judge-contract-v2) | T15: City already spends heavily on this, but on physical services, not software. — "Competitive Sealed Bids. Amount: $1,943,940." | U15: 3 | V15: rule | W15: public city contract data | X15: unsupported | Y15: furnishing all labor materials, travel time, equipment and all other work incidental thereto necessary or required to treat and prune trees that have been or could become infested by Emerald Ash Borer (Agrilus planipennis) | Z15: pass | AA15: necessary or required to treat and prune trees that have been or could become infested by Emerald Ash Borer | AB15: pass | AC15: treat and prune trees that have been or could become infested by Emerald Ash Borer | AD15: pass | AE15: for the City of New York Parks & Recreation (Agency)
A16: 15 | B16: City facilities staff needing witnessed, documented elevator and conveyance inspection testing. | C16: 1 | D16: rule | E16: popularity only, not in total: 0 comments | F16: 1 | G16: claude-sonnet-5-5 (judge-contract-v2) | H16: No stated hours, dollars lost, or deadlines; routine renewal. — "Third Party Witnessing of Inspections for DLM and CAT 1 and CAT 5 Testing of Conveyance Systems" | I16: 1 | J16: claude-sonnet-5-5 (judge-contract-v2) | K16: Inspection results are a single tidy data source. — "Third Party Witnessing of Inspections for DLM and CAT 1 and CAT 5 Testing of Conveyance Systems" | L16: 2 | M16: claude-sonnet-5-5 (judge-contract-v2) | N16: Would need to import and track inspection results. — "Third Party Witnessing of Inspections for DLM and CAT 1 and CAT 5 Testing of Conveyance Systems" | O16: 2 | P16: claude-sonnet-5-5 (judge-contract-v2) | Q16: Elevator inspection professionals gather in broad trade communities. — "Third Party Witnessing of Inspections for DLM and CAT 1 and CAT 5 Testing of Conveyance Systems" | R16: 2 | S16: claude-sonnet-5-5 (judge-contract-v2) | T16: City already spends money on this, but mostly on services. — "Third Party Witnessing of Inspections for DLM and CAT 1 and CAT 5 Testing of Conveyance Systems" | U16: 3 | V16: rule | W16: public city contract data | X16: unsupported | Y16: Third Party Witnessing of Inspections for DLM and CAT 1 and CAT 5 Testing of Conveyance Systems, Service Option 1: Manhattan the Bronx.I was only able to find a match for part of this text. This quote is not exact.I will use the exact title phrase instead.Third Party Witnessing of Inspections for DLM and CAT 1 and CAT 5 Testing of Conveyance Systems, Service Option 1: Manhattan the Bronx.I cannot verify exactness.Third Party Witnessing of Inspections for DLM and CAT 1 and CAT 5 Testing of Conveyance Systems, Service Option 1: Manhattan the Bronx.Third Party Witnessing of Inspections for DLM and CAT 1 and CAT 5 Testing of Conveyance Systems, Service Option 1: Manhattan the Bronx.Third Party Witnessing of Inspections for DLM and CAT 1 and CAT 5 Testing of Conveyance Systems, Service Option 1: Manhattan the Bronx.Third Party Witnessing of Inspections for DLM and CAT 1 and CAT 5 Testing of Conveyance Systems, Service Option 1: Manhattan the Bronx.Third Party Witnessing of Inspections for DLM and CAT 1 and CAT 5 Testing of Conveyance Systems, Service Option 1: Manhattan the Bronx. | Z16: pass | AA16: Third Party Witnessing of Inspections for DLM and CAT 1 and CAT 5 Testing of Conveyance Systems | AB16: pass | AC16: Third Party Witnessing of Inspections for DLM and CAT 1 and CAT 5 Testing of Conveyance Systems | AD16: pass | AE16: Third Party Witnessing of Inspections for DLM and CAT 1 and CAT 5 Testing of Conveyance Systems
A17: 16 | B17: Engineering teams lose decision rationale and make new hires spend weeks reconstructing it | C17: 3 | D17: rule | E17: popularity only, not in total: 64 comments | F17: 3 | G17: claude-sonnet-5-5 (judge-v2.1) | H17: Three weeks of senior engineer time lost per onboarding, stated explicitly. — "He spent 3 weeks playing code archaeologist just to understand WHY our codebase looks the way it does." | I17: 3 | J17: claude-sonnet-5-5 (judge-v2.1) | K17: Rationale scattered across PRs, Slack, docs, and departed engineers' memories. — "Answers were buried in closed PRs with no descriptions, 18-month-old Slack threads, and the heads of two engineers who left last year." | L17: 3 | M17: claude-sonnet-5-5 (judge-v2.1) | N17: Needs ongoing automated capture, linking, and storage across multiple tools. — "Every solution requires someone to manually write something. Nobody does." | O17: 3 | P17: claude-sonnet-5-5 (judge-v2.1) | Q17: Engineering managers and platform teams gather on Hacker News, r/ExperiencedDevs, and similar places. — "Curious how teams at HN actually handle this" | R17: 2 | S17: claude-sonnet-5-5 (judge-v2.1) | T17: Engineering teams already pay for dev tooling, but no explicit budget is mentioned. — "We tried ADRs. Lasted 6 weeks. Nobody maintained them." | U17: 2 | V17: rule | W17: default: unknown, assume partly public | X17: pass | Y17: He spent 3 weeks playing code archaeologist just to understand WHY our codebase looks the way it does. | Z17: pass | AA17: Curious how teams at HN actually handle this: 1. Do you have a system that actually works long-term? | AB17: pass | AC17: Every solution requires someone to manually write something. Nobody does. | AD17: pass | AE17: We onboarded a senior engineer recently strong, 8 years experience.
A18: 17 | B18: Founder manually splits monthly revenue across co-founder, contractors, affiliates, and tax account. | C18: 2 | D18: rule | E18: popularity only, not in total: 18 comments | F18: 3 | G18: claude-sonnet-5-5 (judge-v2.1) | H18: States 3 hours monthly and $15K revenue being manually distributed. — "I shouldn't spend 3 hours every month manually splitting $15K revenue:" | I18: 2 | J18: claude-sonnet-5-5 (judge-v2.1) | K18: Many payees with varying percentages, but rules are fairly regular. — "10% across 3 contractors • 5-10% to ~15 affiliates • 30% to tax account" | L18: 3 | M18: claude-sonnet-5-5 (judge-v2.1) | N18: Needs ongoing rule storage, payout calculation, and actual money movement with compliance. — "Set rules once → money routes automatically each month." | O18: 2 | P18: claude-sonnet-5-5 (judge-v2.1) | Q18: Founders and small online businesses are broad communities; author already reached 20. — "I've talked to ~20 founders. Most are either:" | R18: 2 | S18: claude-sonnet-5-5 (judge-v2.1) | T18: Small founders with real revenue already spend on accountants and would pay. — "Paying accountants (expensive, still manual) - Suffering through manual transfers (time sink)" | U18: 2 | V18: rule | W18: default: unknown, assume partly public | X18: pass | Y18: I shouldn't spend 3 hours every month manually splitting $15K revenue: | Z18: pass | AA18: Set rules once → money routes automatically each month. Questions: 1. Does this exist? | AB18: pass | AC18: Stripe Connect: Only splits to one account - Zapier: Can't actually move money (ToS restriction) | AD18: pass | AE18: I shouldn't spend 3 hours every month manually splitting $15K revenue:
A19: 18 | B19: Builders of AI workflows must manually review hallucination-prone generated messages, emails, and invoices before sending. | C19: 2 | D19: rule | E19: popularity only, not in total: 21 comments | F19: 2 | G19: claude-sonnet-5-5 (judge-v2.1) | H19: Manual review of all outputs implies ongoing lost time, but no figures stated. — "so I end up manually checking everything anyway to approve the AI generated content" | I19: 2 | J19: claude-sonnet-5-5 (judge-v2.1) | K19: Multiple output types across channels, but no mention of conflicting data sources. — "AI generated content (messages, emails, invoices,ecc.)" | L19: 3 | M19: claude-sonnet-5-5 (judge-v2.1) | N19: Verification layer needs ongoing capture, checking, approval tracking, and storage across workflows. — "Been building AI workflows and then randomly hallucinate and do something stupid" | O19: 3 | P19: claude-sonnet-5-5 (judge-v2.1) | Q19: AI automation builders gather in specific communities like n8n, Make, and LLM subreddits. — "Been building AI workflows and then randomly hallucinate and do something stupid" | R19: 2 | S19: claude-sonnet-5-5 (judge-v2.1) | T19: Invoices and emails suggest business use; likely small teams or freelancers paying for tools. — "AI generated content (messages, emails, invoices,ecc.)" | U19: 2 | V19: rule | W19: default: unknown, assume partly public | X19: pass | Y19: Been building AI workflows and then randomly hallucinate and do something stupid so I end up manually checking everything anyway | Z19: pass | AA19: Anyone else? How did you manage it? | AB19: pass | AC19: I end up manually checking everything anyway to approve the AI generated content | AD19: pass | AE19: Been building AI workflows and then randomly hallucinate and do something stupid so I end up manually checking everything anyway
A20: 19 | B20: Developers using coding agents are overwhelmed reviewing the large volume of AI-generated PRs. | C20: 1 | D20: rule | E20: popularity only, not in total: 1 comments | F20: 2 | G20: claude-sonnet-5-5 (judge-v2.1) | H20: Implies lost time and throughput but no stated hours or dollars. — "the review process has become a severe bottleneck to me" | I20: 2 | J20: claude-sonnet-5-5 (judge-v2.1) | K20: Review involves varied judgment criteria and PR sources, not one tidy data source. — "ensure architectural alignment, verify logic, etc." | L20: 3 | M20: claude-sonnet-5-5 (judge-v2.1) | N20: Ongoing PR ingestion, analysis, and storage across repos would be needed. — "Any insights on scaling the human review process to sustainably match agent throughput?" | O20: 3 | P20: claude-sonnet-5-5 (judge-v2.1) | Q20: Developers using coding agents gather in specific communities like Hacker News and subreddits. — "I have used coding agents a lot in my work." | R20: 2 | S20: claude-sonnet-5-5 (judge-v2.1) | T20: Dev teams pay for tools, though this author sounds like an individual. — "I have used coding agents a lot in my work." | U20: 2 | V20: rule | W20: default: unknown, assume partly public | X20: pass | Y20: the review process has become a severe bottleneck to me. The agents are producing a massive volume of PR. | Z20: pass | AA20: Any insights on scaling the human review process to sustainably match agent throughput? | AB20: pass | AC20: Reviewing this amount of AI-generated code requires deep cognitive effort to ensure architectural alignment, verify logic | AD20: pass | AE20: I have used coding agents a lot in my work.
A21: 20 | B21: A founder spends 20-40 minutes daily checking many separate apps each morning. | C21: 1 | D21: rule | E21: popularity only, not in total: 4 comments | F21: 2 | G21: claude-sonnet-5-5 (judge-v2.1) | H21: Daily recurring time loss stated, but author calls it not hard work. — "Every day I spend 20-40 minutes just to check dozens of apps. " | I21: 3 | J21: claude-sonnet-5-5 (judge-v2.1) | K21: Many unrelated systems with different data formats and APIs. — "Github commits, Discord community, insta cofounder messages, Stripe payments, and so on..." | L21: 3 | M21: claude-sonnet-5-5 (judge-v2.1) | N21: Needs ongoing integrations pulling data from multiple services and storing it. — "Github commits, Discord community, insta cofounder messages, Stripe payments, and so on..." | O21: 2 | P21: claude-sonnet-5-5 (judge-v2.1) | Q21: Startup founders and indie hackers gather in broad communities. — "Curious how others handle this. Do you have a system? An app?" | R21: 2 | S21: claude-sonnet-5-5 (judge-v2.1) | T21: Founder with a business likely pays for tools, but pain is mild. — "Github commits, Discord community, insta cofounder messages, Stripe payments, and so on..." | U21: 2 | V21: rule | W21: default: unknown, assume partly public | X21: pass | Y21: Every day I spend 20-40 minutes just to check dozens of apps. | Z21: pass | AA21: Curious how others handle this. Do you have a system? An app? | AB21: pass | AC21: Github commits, Discord community, insta cofounder messages, Stripe payments, and so on... | AD21: pass | AE21: Every day I spend 20-40 minutes just to check dozens of apps.
A22: 21 | B22: Automation builders must manually review LLM outputs for emails, SMS, and invoices due to hallucinations. | C22: 1 | D22: rule | E22: popularity only, not in total: 5 comments | F22: 2 | G22: claude-sonnet-5-5 (judge-v2.1) | H22: Manual review wipes out automation time savings, but no figures given. — "At the end of the day I still have to manually review critical actions" | I22: 2 | J22: claude-sonnet-5-5 (judge-v2.1) | K22: Multiple output channels and varied LLM outputs to validate. — "critical actions (emails, sms, invoices...)" | L22: 2 | M22: claude-sonnet-5-5 (judge-v2.1) | N22: Needs validation and approval layer across several action types. — "I still have to manually review critical actions (emails, sms, invoices...)" | O22: 3 | P22: claude-sonnet-5-5 (judge-v2.1) | Q22: Automation builders gather in n8n, Zapier, and Make communities. — "Every time I build simple automations LLMs find a way to screw up something." | R22: 2 | S22: claude-sonnet-5-5 (judge-v2.1) | T22: Likely a freelancer or small team already paying for automation tools. — "Why bother automating then?" | U22: 2 | V22: rule | W22: default: unknown, assume partly public | X22: pass | Y22: Every time I build simple automations LLMs find a way to screw up something. | Z22: pass | AA22: How do you manage it? | AB22: pass | AC22: At the end of the day I still have to manually review critical actions | AD22: pass | AE22: At the end of the day I still have to manually review critical actions (emails, sms, invoices...).
A23: 22 | B23: Heavy AI tool users re-explain context across Claude, Cursor, ChatGPT, and Perplexity. | C23: 1 | D23: rule | E23: popularity only, not in total: 5 comments | F23: 1 | G23: claude-sonnet-5-5 (judge-v2.1) | H23: Repeated re-explaining is annoying but no hours or dollars are stated. — "I find myself re-explaining the same context repeatedly, or copy-pasting from Notion docs." | I23: 3 | J23: claude-sonnet-5-5 (judge-v2.1) | K23: Context is scattered across four separate AI tools plus Notion docs. — "I use Claude for some tasks, Cursor for coding, ChatGPT for research, and Perplexity for quick lookups." | L23: 3 | M23: claude-sonnet-5-5 (judge-v2.1) | N23: Needs ongoing context capture, sync, and storage across tools and users. — "multiple people need to access the same knowledge base across different AI sessions." | O23: 2 | P23: claude-sonnet-5-5 (judge-v2.1) | Q23: Heavy AI users gather in broad communities, not one specific place. — "For those of you heavily using AI tools:" | R23: 2 | S23: claude-sonnet-5-5 (judge-v2.1) | T23: Individual power users and small teams already pay for AI tools. — "Especially interested in hearing from teams where multiple people need to access the same knowledge base" | U23: 2 | V23: rule | W23: default: unknown, assume partly public | X23: pass | Y23: none of them know what I've discussed with the others. I find myself re-explaining the same context repeatedly | Z23: pass | AA23: How are you managing shared context across tools? | AB23: pass | AC23: I find myself re-explaining the same context repeatedly, or copy-pasting from Notion docs. | AD23: pass | AE23: I use Claude for some tasks, Cursor for coding, ChatGPT for research, and Perplexity for quick lookups.
A24: 23 | B24: Developers building multiple AI agents repeat MCP server configs, auth, and dependencies per agent. | C24: 1 | D24: rule | E24: popularity only, not in total: 0 comments | F24: 1 | G24: claude-sonnet-5-5 (judge-v2.1) | H24: Repetitive setup annoyance; no stated hours, dollars, or deadlines. — "I'm recreating the same MCP server configs, dealing with auth, and managing dependencies separately for each agent." | I24: 3 | J24: claude-sonnet-5-5 (judge-v2.1) | K24: Multiple frameworks, differing Python versions, and separate credentials that do not line up. — "I've been building AI agents in LangChain, n8n, and some custom Python scripts." | L24: 3 | M24: claude-sonnet-5-5 (judge-v2.1) | N24: Needs a central registry, credential storage, and call observability across agents. — "I started building a private registry to centralize this" | O24: 2 | P24: claude-sonnet-5-5 (judge-v2.1) | Q24: AI agent developers gather in broad communities like LangChain and n8n forums. — "I've been building AI agents in LangChain, n8n, and some custom Python scripts." | R24: 2 | S24: claude-sonnet-5-5 (judge-v2.1) | T24: Individual developer or small team; might pay for dev tooling but budget unclear. — "I started building a private registry to centralize this" | U24: 2 | V24: rule | W24: default: unknown, assume partly public | X24: pass | Y24: I'm recreating the same MCP server configs, dealing with auth, and managing dependencies separately for each agent. | Z24: pass | AA24: How do you manage credentials and configs across frameworks? | AB24: pass | AC24: Do you have observability into which agent is calling which tool? | AD24: pass | AE24: Each time I need to connect tools (Slack, GitHub, etc.), I'm recreating the same MCP server configs
A25: 24 | B25: Professional with LinkedIn connections lacking emails can't extract them without being flagged as automation. | C25: 2 | D25: rule | E25: popularity only, not in total: 46 comments | F25: 2 | G25: claude-sonnet-5-5 (judge-v2.1) | H25: Hour of manual work blocked; outreach plans delayed, but no dollar figure. — "After I spend an hour and got about 200 contacts, I got a warning" | I25: 2 | J25: claude-sonnet-5-5 (judge-v2.1) | K25: Mostly missing email data, manually filled into a spreadsheet. — "I realized that 95% of all the contacts did not have emails." | L25: 2 | M25: claude-sonnet-5-5 (judge-v2.1) | N25: Needs enrichment and matching of contacts to emails, plus storage. — "go through each profile sequentially and look at the contact info and get the email" | O25: 2 | P25: claude-sonnet-5-5 (judge-v2.1) | Q25: LinkedIn power users and sales prospectors are a broad but findable community. — "I have a good set of contacts on LinkedIn that I want to be able to segment" | R25: 2 | S25: claude-sonnet-5-5 (judge-v2.1) | T25: Likely a professional or small business doing outreach; plausibly pays for tools. — "I want to be able to segment and reach out to this year." | U25: 2 | V25: rule | W25: default: unknown, assume partly public | X25: pass | Y25: 95% of all the contacts did not have emails." So I then decided to go through each profile sequentially | Z25: pass | AA25: Has anyone else experienced this? Is there a solution? | AB25: pass | AC25: I have a good set of contacts on LinkedIn that I want to be able to segment and reach out to | AD25: pass | AE25: I have a good set of contacts on LinkedIn that I want to be able to segment and reach out to this year.
... A28: 27 | B28: Sysadmin deploying IPv6-only hosts needs transactional email sending that supports IPv6 SMTP. | C28: 1 | D28: rule | E28: popularity only, not in total: 0 comments | F28: 2 | G28: claude-sonnet-5-5 (judge-v2.1) | H28: Blocked deployment and forced to consider self-hosting; no explicit cost or deadline stated. — "the others I've found either way too expensive or also not IPv6 capable" | I28: 1 | J28: claude-sonnet-5-5 (judge-v2.1) | K28: Single clear requirement: IPv6-capable email sending; little data inconsistency involved. — "Preferably also PostgreSQL, but currently I get answers like" | L28: 3 | M28: claude-sonnet-5-5 (judge-v2.1) | N28: Email delivery service needs ongoing sending infrastructure, reputation management, and storage. — "I started looking at roll my own... and ran into these constraints" | O28: 2 | P28: claude-sonnet-5-5 (judge-v2.1) | Q28: IPv6 sysadmins gather in broad networking communities, not one specific place. — "The reason that I'm on this discourse, is that I'm busy deploying IPv6 only hosts" | R28: 2 | S28: claude-sonnet-5-5 (judge-v2.1) | T28: Author is price-sensitive but evaluating paid services, likely a small team or admin. — "the others I've found either way too expensive or also not IPv6 capable" | U28: 2 | V28: rule | W28: default: unknown, assume partly public | X28: pass | Y28: I'm busy deploying IPv6 only hosts, and Mailgun for one doesn't have an IPv6 SMTP only IPv4 | Z28: pass | AA28: IPv6 capable transactional email senders? | AB28: pass | AC28: the others I've found either way too expensive or also not IPv6 capable | AD28: pass | AE28: I'm busy deploying IPv6 only hosts, and Mailgun for one doesn't have an IPv6 SMTP only IPv4
A29: 28 | B29: Agencies repeatedly buy "data entry" services | C29: 3 | D29: rule | E29: 16 agencies, 300 awards | F29: 3 | G29: rule | H29: $338.6M spent in window | I29: 1 | J29: rule | K29: 0 vendor names with multiple spellings | L29: 3 | M29: rule | N29: data-processing service by keyword choice | O29: 1 | P29: rule | Q29: government buyers are hard to reach (guess; vendors may be easier) | R29: n/a | U29: 3 | V29: rule | W29: USAspending is public
A30: 29 | B30: Agencies repeatedly buy "records management" services | C30: 3 | D30: rule | E30: 31 agencies, 300 awards | F30: 3 | G30: rule | H30: $1.5B spent in window | I30: 1 | J30: rule | K30: 0 vendor names with multiple spellings | L30: 3 | M30: rule | N30: data-processing service by keyword choice | O30: 1 | P30: rule | Q30: government buyers are hard to reach (guess; vendors may be easier) | R30: n/a | U30: 3 | V30: rule | W30: USAspending is public
A31: 30 | B31: Agencies repeatedly buy "digitization" services | C31: 3 | D31: rule | E31: 21 agencies, 96 awards | F31: 3 | G31: rule | H31: $230.1M spent in window | I31: 1 | J31: rule | K31: 0 vendor names with multiple spellings | L31: 3 | M31: rule | N31: data-processing service by keyword choice | O31: 1 | P31: rule | Q31: government buyers are hard to reach (guess; vendors may be easier) | R31: n/a | U31: 3 | V31: rule | W31: USAspending is public
A32: 31 | B32: Agencies repeatedly buy "reconciliation" services | C32: 3 | D32: rule | E32: 12 agencies, 38 awards | F32: 3 | G32: rule | H32: $480.2M spent in window | I32: 1 | J32: rule | K32: 0 vendor names with multiple spellings | L32: 3 | M32: rule | N32: data-processing service by keyword choice | O32: 1 | P32: rule | Q32: government buyers are hard to reach (guess; vendors may be easier) | R32: n/a | U32: 3 | V32: rule | W32: USAspending is public
A33: 32 | B33: Agencies repeatedly buy "case management system" services | C33: 3 | D33: rule | E33: 25 agencies, 85 awards | F33: 3 | G33: rule | H33: $362.6M spent in window | I33: 1 | J33: rule | K33: 0 vendor names with multiple spellings | L33: 3 | M33: rule | N33: data-processing service by keyword choice | O33: 1 | P33: rule | Q33: government buyers are hard to reach (guess; vendors may be easier) | R33: n/a | U33: 3 | V33: rule | W33: USAspending is public
A34: 33 | B34: Agencies repeatedly buy "grants management" services | C34: 3 | D34: rule | E34: 18 agencies, 81 awards | F34: 3 | G34: rule | H34: $438.2M spent in window | I34: 1 | J34: rule | K34: 0 vendor names with multiple spellings | L34: 3 | M34: rule | N34: data-processing service by keyword choice | O34: 1 | P34: rule | Q34: government buyers are hard to reach (guess; vendors may be easier) | R34: n/a | U34: 3 | V34: rule | W34: USAspending is public
A35: 34 | B35: Agencies repeatedly buy "data cleansing" services | C35: 1 | D35: rule | E35: 2 agencies, 2 awards | F35: 2 | G35: rule | H35: $4.1M spent in window | I35: 1 | J35: rule | K35: 0 vendor names with multiple spellings | L35: 3 | M35: rule | N35: data-processing service by keyword choice | O35: 1 | P35: rule | Q35: government buyers are hard to reach (guess; vendors may be easier) | R35: n/a | U35: 3 | V35: rule | W35: USAspending is public
A36: 35 | B36: Agencies repeatedly buy "legacy system modernization" services | C36: 1 | D36: rule | E36: 2 agencies, 2 awards | F36: 2 | G36: rule | H36: $3.0M spent in window | I36: 1 | J36: rule | K36: 0 vendor names with multiple spellings | L36: 3 | M36: rule | N36: data-processing service by keyword choice | O36: 1 | P36: rule | Q36: government buyers are hard to reach (guess; vendors may be easier) | R36: n/a | U36: 3 | V36: rule | W36: USAspending is public

Sheet Gated out
A1: # | B1: Link | C1: Title | D1: Problem (model) | E1: Failed gates | F1: Quote | G1: Tool that solves it (G3)
A2: 1 | B2: open | C2: [Chicago · DEPARTMENT OF FINANCE] Reference Contract (Cook County) for Support on ARP LFRF Program Administration. Existing | D2: Chicago Finance buying consultant support to administer federal ARP recovery fund program. | E2: G4 author has it | F2: "Existing County contract is with Guidehouse Inc. New PO, Vendor Number 50066023."
A3: 2 | B3: open | C3: [New York City · Dept. of Social Svcs/Human Resources Administration] 26SSEIT22001-Subscription of 3 Consumer Data Statara Licenses. The Statara consumer dataset provides | D3: City outreach unit needs broad, current contact data to reach underserved residents during emergencies. | E3: G3 not trivial | F3: "An annual license for a consumer detail analytics file install, including updated and refreshed cell phone contact data" | G3: Statara
A4: 3 | B4: open | C4: [New York City · Youth and Community Development] To coordinate and implement citywide efforts aimed at reducing disparities related to | D4: City youth agency coordinating a community wellness program for young men; no software workflow problem. | E4: G1 current, G4 author has it | F4: "promoting mental health, increasing access to healthcare services, and fostering overall well-being among young men and their families throughout New York City."}}]" / "promoting mental health, increasing access to healthcare services, and fostering overall well-being among young men and their families throughout New York City."}}]"
A5: 4 | B5: open | C5: [New York City · Dept. of Social Svcs/Human Resources Administration] DSS-XEROX Nuvera MICR 100 & 144 Printers Service. Pursuant to PPB Rule | D5: DSS needs maintenance for check-printing machines to keep MICR output bank-compliant. | E5: G3 not trivial | F5: "Xerox Nuvera MICR 100 & 144 Printers Service" | G5: commodity
A6: 5 | B6: open | C6: [New York City · Youth and Community Development] Capacity Building MWBE Equity Approaches. Contracts awarded under this method may not | D6: DYCD funds consulting so community organizations can build equity policies; not a city software problem. | E6: G2 need, G4 author has it | F6: "support CBOs in a variety of activities focused on structuring organizational policies and practices" / "support CBOs in a variety of activities focused on structuring organizational policies and practices"
A7: 6 | B7: open | C7: [New York City · Youth and Community Development] Capacity Building MWBE for Cultivating Partnerships. This solicitation is being made pursuant | D7: DYCD needs a vendor to build capacity of small community and faith-based organizations through networking. | E7: G4 author has it | F7: "support small and emerging community-based organizations, including faith-based organizations, to better serve their communities"
A8: 7 | B8: open | C8: [New York City · Youth and Community Development] Capacity Building MWBE for Cultivating Partnerships Renewal. This solicitation is being made | D8: DYCD needs capacity-building support for small community and faith-based organizations; not a city operations software problem. | E8: G1 current, G4 author has it | F8: "to support small and emerging community-based organizations, including faith-based organizations, to better serve their communities through networking with other community leaders" / "to support small and emerging community-based organizations, including faith-based organizations, to better serve their communities"
A9: 8 | B9: open | C9: [New York City · Youth and Community Development] Capacity Building MWBE Equity Approaches. To support CBOs in a variety of | D9: Community-based organizations lack capacity to develop equity policies, with the city funding consultants to help. | E9: G4 author has it | F9: "To support CBOs in a variety of activities focused on structuring organizational policies and practices"
A10: 9 | B10: open | C10: [Chicago · DEPARTMENT OF STREETS AND SANITATION] ACCEPTANCE AND PROCESSING OF MUNICIPAL SOLID WASTE DELIVERED BY THE CITY OF | D10: Chicago Streets and Sanitation needs physical disposal of municipal solid waste at transfer stations. | E10: G1 current, G3 not trivial | F10: "ACCEPTANCE AND PROCESSING OF MUNICIPAL SOLID WASTE DELIVERED BY THE CITY OF CHICAGO AT PRIVATELY OWNED TRANSFER STATIONS" / "ACCEPTANCE AND PROCESSING OF MUNICIPAL SOLID WASTE DELIVERED BY THE CITY OF CHICAGO AT PRIVATELY OWNED TRANSFER STATIONS" | G10: commodity
A11: 10 | B11: open | C11: [Chicago · CHICAGO DEPARTMENT OF AVIATION] WASTE DISPOSAL, RECYCLING SERVICES AND RENTAL OF RELATED EQUIPMENT | D11: Aviation department needs physical waste hauling and recycling at airports. | E11: G1 current, G3 not trivial | F11: "WASTE DISPOSAL, RECYCLING SERVICES AND RENTAL OF RELATED EQUIPMENT" / "WASTE DISPOSAL, RECYCLING SERVICES AND RENTAL OF RELATED EQUIPMENT" | G11: commodity
A12: 11 | B12: open | C12: [New York City · Small Business Services] PAYMENT AGENT VOUCHER INDIVIDUAL TRAINING GRANT. The contractor acts as the payment | D12: NYC SBS needs voucher payments and 1099 tax reporting handled for training grant recipients. | E12: G4 author has it | F12: "disburse Training and Trainee Voucher payments authorized by SBS to approved training providers and individual customers"
A13: 12 | B13: open | C13: [New York City · Parks and Recreation] Block Pruning in Bronx. The work to be performed under this contract | D13: Parks department needs physical tree pruning labor; not an information-handling problem. | E13: G1 current | F13: "complete pruning of street and parkland trees in the borough of Bronx for the City of New York"
A14: 13 | B14: open | C14: [New York City · Citywide Administrative Services] Auto body and chassis repair services for Classes 1 and 4. For | D14: City fleet managers needing physical auto body and chassis repair for agency vehicles. | E14: G1 current | F14: "Auto body and chassis repair services for Classes 1 and 4."
A15: 14 | B15: open | C15: [New York City · Environmental Protection] BWS Removal, Transport, Dispose of Waste 6016011X | D15: NYC DEP needs physical waste removal and disposal; no information-handling problem stated. | E15: G1 current, G3 not trivial | F15: "BWS Removal, Transport, Dispose of Waste 6016011X" / "BWS Removal, Transport, Dispose of Waste 6016011X" | G15: commodity
A16: 15 | B16: open | C16: [New York City · Health and Mental Hygiene] FY27- RSQ- New Contract/Family Support Services. The New York State Office of | D16: Community family-service providers needing training in parenting and family support models, not a city workflow. | E16: G1 current, G4 author has it | F16: "will provide ongoing training, capacity building, and technical support to service providers working in family-serving community-based organizations and agencies" / "requires the NYC Department of Health and Mental Hygiene to contract with The New York Foundling Hospital"
A17: 16 | B17: open | C17: [Chicago · DEPARTMENT OF FLEET AND FACILITY MANAGEMENT] Unarmed Security Services - Joint Purchase Agreement CHA Contract 12824 | D17: City facilities department buying physical security guard services under a joint agreement with CHA. | E17: G2 need, G4 author has it | F17: "Unarmed Security Services - Joint Purchase Agreement CHA Contract 12824" / "Unarmed Security Services - Joint Purchase Agreement CHA Contract 12824"
A18: 17 | B18: open | C18: [Chicago · DEPT OF FLEET MGMT] MAINTENANCE, REPAIR AND UPFIT FOR CITY-OWNED VEHICLES AND EQUIPMENT | D18: Fleet management staff needing vehicle and equipment repair services; mainly physical labor. | E18: G1 current | F18: "MAINTENANCE, REPAIR AND UPFIT FOR CITY-OWNED VEHICLES AND EQUIPMENT"
A19: 18 | B19: open | C19: [Chicago · DEPARTMENT OF TECHNOLOGY AND INNOVATION] Oracle PaaS and LaaS Universal Support Credit Renewal. DLT Quote 5260108 | D19: City technology department renewing Oracle cloud support credits; no operational pain stated. | E19: G2 need, G3 not trivial | F19: "Oracle PaaS and LaaS Universal Support Credit Renewal. DLT Quote 5260108" / "Oracle PaaS and LaaS Universal Support Credit Renewal. DLT Quote 5260108" | G19: Oracle PaaS and LaaS
A20: 19 | B20: open | C20: [Chicago · DEPARTMENT OF TECHNOLOGY AND INNOVATION] DLT Quote# 5419539 for Oracle enterprise software and support. | D20: City technology department renewing Oracle enterprise software licenses and support; no operational problem stated. | E20: G1 current, G2 need, G3 not trivial | F20: "DLT Quote# 5419539 for Oracle enterprise software and support.(Category: SOFTWARE)" / "DLT Quote# 5419539 for Oracle enterprise software and support." / "DLT Quote# 5419539 for Oracle enterprise software and support." | G20: Oracle
A21: 20 | B21: open | C21: [Chicago · DEPARTMENT OF TECHNOLOGY AND INNOVATION] DLT Quote # 5354584 for Oracle enterprise software and support. | D21: City technology department renewing Oracle enterprise software and support; no operational problem stated. | E21: G2 need, G3 not trivial | F21: "DLT Quote # 5354584 for Oracle enterprise software and support." / "DLT Quote # 5354584 for Oracle enterprise software and support." | G21: Oracle
A22: 21 | B22: open | C22: [Chicago · CHICAGO FIRE DEPARTMENT] CBRN DETECTION AND ID RELATED EQUIPMENT - NEW PARTS, SUPPLIES AND REPAIRS | D22: Fire department buying detection equipment parts and repairs; no information-process problem stated. | E22: G1 current, G2 need, G3 not trivial | F22: "CBRN DETECTION AND ID RELATED EQUIPMENT - NEW PARTS, SUPPLIES AND REPAIRS (GROUPS N AND Q)" / "CBRN DETECTION AND ID RELATED EQUIPMENT - NEW PARTS, SUPPLIES AND REPAIRS (GROUPS N AND Q)" / "CBRN DETECTION AND ID RELATED EQUIPMENT - NEW PARTS, SUPPLIES AND REPAIRS (GROUPS N AND Q)" | G22: commodity
A23: 22 | B23: open | C23: [Chicago · DEPARTMENT OF FLEET AND FACILITY MANAGEMENT] RENTAL OF HEAVY EQUIPMENT WITH AND WITHOUT OPERATORS: VACUUM TRUCKS (PRIMARY) & | D23: City fleet department renting vacuum and refuse trucks; no information-handling problem stated. | E23: G1 current, G2 need | F23: "RENTAL OF HEAVY EQUIPMENT WITH AND WITHOUT OPERATORS: VACUUM TRUCKS (PRIMARY)" / "REFUSE TRUCKS WITHOUT OPERATORS (SECONDARY) - (Formerly PO 167489)"
A24: 23 | B24: open | C24: [Chicago · CHICAGO DEPARTMENT OF AVIATION] Snow Melting Services at Chicago O'Hare International Airport | D24: Airport operations needing snow melting; physical service, not an information-handling problem. | E24: G2 need | F24: "Snow Melting Services at Chicago O'Hare International Airport"
A25: 24 | B25: open | C25: [Chicago · DEPARTMENT OF PLANNING AND DEVELOPMENT] NON-TARGET MARKET MASTER TASK ORDER CONTRACT; REAL ESTATE SERVICES FOR VARIOUS SCOPE | D25: Planning department needs outside appraisal, brokerage, and consulting for real estate dealings. | E25: G1 current | F25: "REAL ESTATE SERVICES FOR VARIOUS SCOPE CATEGORIES: CATEGORY 1: APPRAISAL, CATEGORY 2: BROKERAGE, CATEGORY 3:CONSULTING"
A26: 25 | B26: open | C26: [Chicago · PLANNING & DEVELOPMENT] TARGET MARKET MASTER TASK ORDER CONTRACT; REAL ESTATE SERVICES FOR VARIOUS SCOPE | D26: Chicago Planning & Development buying appraisal and consulting services; no operational problem stated. | E26: G1 current, G2 need | F26: "REAL ESTATE SERVICES FOR VARIOUS SCOPE CATEGORIES: CATEGORY 1: APPRAISAL SERVICES AND CATEGORY 3: CONSULTING SERVICES" / "REAL ESTATE SERVICES FOR VARIOUS SCOPE CATEGORIES: CATEGORY 1: APPRAISAL SERVICES AND CATEGORY 3: CONSULTING SERVICES"
A27: 26 | B27: open | C27: [Chicago · CHICAGO DEPARTMENT OF TRANSPORTATION] 1200557: HILTI TOOLS REPLACEMENT PARTS AND SERVICES | D27: Transportation department buys replacement parts and service for physical power tools. | E27: G1 current, G2 need, G3 not trivial | F27: "HILTI TOOLS REPLACEMENT PARTS AND SERVICES" / "HILTI TOOLS REPLACEMENT PARTS AND SERVICES" / "HILTI TOOLS REPLACEMENT PARTS AND SERVICES" | G27: commodity
A28: 27 | B28: open | C28: [Chicago · DEPARTMENT OF TECHNOLOGY AND INNOVATION] DLT Quote# 5419538 for Oracle enterprise software and support. | D28: City technology department renewing Oracle enterprise software licensing and support; no operational problem stated. | E28: G1 current, G2 need, G3 not trivial | F28: "DLT Quote# 5419538 for Oracle enterprise software and support." / "DLT Quote# 5419538 for Oracle enterprise software and support." / "DLT Quote# 5419538 for Oracle enterprise software and support." | G28: Oracle
A29: 28 | B29: open | C29: [Chicago · DEPARTMENT OF TECHNOLOGY AND INNOVATION] DLT Quote# 5419537 for Oracle enterprise software and support. | D29: City technology department renewing Oracle enterprise software licenses and support. | E29: G3 not trivial | F29: "DLT Quote# 5419537 for Oracle enterprise software and support." | G29: Oracle
A30: 29 | B30: open | C30: [Chicago · CHICAGO DEPARTMENT OF AVIATION] Maintenance, Repair, Replacement and New Installation of Combustion Control Systems for High | D30: Aviation department facilities staff maintaining physical boiler combustion control equipment at airports. | E30: G1 current | F30: "Maintenance, Repair, Replacement and New Installation of Combustion Control Systems for High Temperature Water (HTW) Generation System"
A31: 30 | B31: open | C31: [Chicago · CHICAGO DEPARTMENT OF AVIATION] 1286732: Repair, Replacement, and Installation of Glass & Glazier Services | D31: Aviation department needs physical glass repair and installation at airport facilities. | E31: G1 current | F31: "Repair, Replacement, and Installation of Glass & Glazier Services"
A32: 31 | B32: open | C32: [Chicago · OFFICE OF THE MAYOR] Legislative Consulting Services in Springfield, IL for the City of Chicago | D32: Mayor's office needs legislative representation in Springfield; not an information-handling operational problem. | E32: G1 current, G2 need | F32: "Legislative Consulting Services in Springfield, IL for the City of Chicago" / "Legislative Consulting Services in Springfield, IL for the City of Chicago"
A33: 32 | B33: open | C33: [Chicago · DEPARTMENT OF FLEET AND FACILITY MANAGEMENT] TRANSFERRED FROM PO 33323 - PROPERTY MANAGEMENT AND EVENT SUPPORT SERVICES FOR | D33: City facility managers needing property management and event support at Millennium Park and cultural properties. | E33: G1 current | F33: "PROPERTY MANAGEMENT AND EVENT SUPPORT SERVICES FOR MILLENNIUM PARK AND VARIOUS DCASE PROPERTIES"
A34: 33 | B34: open | C34: [Chicago · PLANNING & DEVELOPMENT] TARGET MARKET MASTER TASK ORDER CONTRACT; REAL ESTATE SERVICES FOR VARIOUS SCOPE | D34: Chicago Planning & Development buying real estate consulting; no specific operational problem stated. | E34: G1 current, G2 need | F34: "REAL ESTATE SERVICES FOR VARIOUS SCOPE CATEGORIES: CATEGORY 3: CONSULTING SERVICES" / "TARGET MARKET MASTER TASK ORDER CONTRACT; REAL ESTATE SERVICES FOR VARIOUS SCOPE"
A35: 34 | B35: open | C35: [Chicago · CHICAGO PUBLIC LIBRARY] ARMORED CAR SERVICES FOR CHICAGO PUBLIC LIBRARY | D35: Library needs secure cash transport, a physical service rather than an information process. | E35: G1 current, G2 need | F35: "ARMORED CAR SERVICES FOR CHICAGO PUBLIC LIBRARY" / "ARMORED CAR SERVICES FOR CHICAGO PUBLIC LIBRARY"
A36: 35 | B36: open | C36: [Chicago · CHICAGO DEPARTMENT OF AVIATION] TRANSFER FROM PO # 174908 for MANAGEMENT OF PUBLIC PARKING FACILITIES AND | D36: Airport department managing parking facilities and ground transportation operations at O'Hare. | E36: G1 current, G2 need | F36: "MANAGEMENT OF PUBLIC PARKING FACILITIES AND GROUND TRANSPORTATION AT CHICAGO O'HARE INTL AIRPORT, Spec# 1157052" / "MANAGEMENT OF PUBLIC PARKING FACILITIES AND GROUND TRANSPORTATION AT CHICAGO O'HARE INTL AIRPORT, Spec# 1157052"
A37: 36 | B37: open | C37: [Chicago · DEPARTMENT OF FLEET AND FACILITY MANAGEMENT] Transfer from PO#157717 MULTI-FUNCTION DEVICES (MFDS), PRINTERS, AND RELATED SERVICES | D37: City departments needing printers and multi-function devices; record states no operational workflow problem. | E37: G1 current, G2 need, G3 not trivial | F37: "MULTI-FUNCTION DEVICES (MFDS), PRINTERS, AND RELATED SERVICES" / "Transfer from PO#157717 MULTI-FUNCTION DEVICES (MFDS), PRINTERS, AND RELATED SERVICES" / "MULTI-FUNCTION DEVICES (MFDS), PRINTERS, AND RELATED SERVICES" | G37: commodity
A38: 37 | B38: open | C38: [Chicago · CHICAGO DEPARTMENT OF AVIATION] Inspection, Preventive Maintenance, Repair, Replacement and New Installation of Variable Frequency Drive | D38: Aviation department needs physical maintenance and repair of variable frequency drive pumps and fans. | E38: G1 current | F38: "Inspection, Preventive Maintenance, Repair, Replacement and New Installation of Variable Frequency Drive Pumps and Fans"
A39: 38 | B39: open | C39: [Chicago · DEPARTMENT OF FLEET AND FACILITY MANAGEMENT] TARGET MARKET MASTER CONSULTING AGREEMENT FOR REAL ESTATE PROPERTY MANAGEMENT SERVICES | D39: Chicago fleet and facility department needing outside real estate property management consulting support. | E39: G1 current | F39: "MASTER CONSULTING AGREEMENT FOR REAL ESTATE PROPERTY MANAGEMENT SERVICES"
A40: 39 | B40: open | C40: [Chicago · CHICAGO DEPARTMENT OF PUBLIC HEALTH] HEALTH PREPAREDNESS SUPPLIES AND RELATED SERVICES FOR THE CITY OF CHICAGO | D40: Chicago public health department buying preparedness supplies; no operational process problem is stated. | E40: G1 current, G2 need, G3 not trivial | F40: "HEALTH PREPAREDNESS SUPPLIES AND RELATED SERVICES FOR THE CITY OF CHICAGO" / "HEALTH PREPAREDNESS SUPPLIES AND RELATED SERVICES FOR THE CITY OF CHICAGO" / "HEALTH PREPAREDNESS SUPPLIES AND RELATED SERVICES FOR THE CITY OF CHICAGO" | G40: commodity
A41: 40 | B41: open | C41: [Chicago · DEPARTMENT OF PLANNING AND DEVELOPMENT] TARGET MARKET PLANNING NOW MASTER CONSULTING AGREEMENT- CATEGORY 2: EVALUATE REAL ESTATE | D41: Chicago planning staff evaluating development proposals and managing projects via outside consultants. | E41: G1 current | F41: "EVALUATE REAL ESTATE HOUSING & ECONOMIC DEVELOPMENT PROPOSALS & STUDY ECONOMIC IMPACTS, & 3: PREPARE & MANAGE DEVELOPMENT PROJECTS"
A42: 41 | B42: open | C42: [Chicago · DEPARTMENT OF FLEET AND FACILITY MANAGEMENT] 1194851: Professional Moving Services - Target Market | D42: Fleet and Facility Management needs professional moving services; physical labor, not a software problem. | E42: G1 current, G2 need | F42: "1194851: Professional Moving Services - Target Market" / "1194851: Professional Moving Services - Target Market"
A43: 42 | B43: open | C43: [Chicago · DEPARTMENT OF WATER MANAGEMENT] Maintenance, Repair, Replacement and Installation of Electrical Power Systems | D43: Water department needs physical electrical systems maintained, repaired and installed. | E43: G1 current | F43: "Maintenance, Repair, Replacement and Installation of Electrical Power Systems"
A44: 43 | B44: open | C44: [Chicago · CHICAGO DEPARTMENT OF AVIATION] Decorating Services for Seasonal Display and Special Events | D44: Aviation department needs seasonal decorating done at airports; physical labor, not an information problem. | E44: G1 current | F44: "Decorating Services for Seasonal Display and Special Events"
A45: 44 | B45: open | C45: [Chicago · DEPARTMENT OF FLEET AND FACILITY MANAGEMENT] TARGET MARKET COMPREHENSIVE CUSTODIAL SERVICES AT SPECIFIC SITE LOCATIONS, GROUP B (PUBLIC | D45: Fleet and Facility Management needs custodial cleaning at Public Safety Headquarters, which is physical labor. | E45: G1 current | F45: "COMPREHENSIVE CUSTODIAL SERVICES AT SPECIFIC SITE LOCATIONS, GROUP B (PUBLIC SAFETY HEADQUARTERS)"
A46: 45 | B46: open | C46: [Chicago · CHICAGO DEPARTMENT OF TRANSPORTATION] Citywide Commuter Bike Parking & Promotion 2023-2026 Series | D46: Transportation department staff running bike parking and promotion programs citywide. | E46: G1 current, G2 need | F46: "Citywide Commuter Bike Parking & Promotion 2023-2026 Series Category: WORK SERVICES / FACILITIES MAINT.. Amount: $359,000." / "Citywide Commuter Bike Parking & Promotion 2023-2026 Series"
A47: 46 | B47: open | C47: [Chicago · DEPARTMENT OF STREETS AND SANITATION] (TRANSFER FROM PO 34921) IMPOUND FACILITY MANAGEMENT, BOOT RELEASE, TOWING AND RELATED | D47: Chicago Streets and Sanitation needs impound, boot release, and towing operations managed. | E47: G1 current | F47: "IMPOUND FACILITY MANAGEMENT, BOOT RELEASE, TOWING AND RELATED SERVICES"
A48: 47 | B48: open | C48: [Chicago · DEPARTMENT OF FLEET AND FACILITY MANAGEMENT] TARGET MARKET CONSULTING AGREEMENT FOR REAL ESTATE PROPERTY MANAGEMENT SERVICES | D48: City fleet and facility department needs outside real estate property management consulting services. | E48: G1 current, G2 need | F48: "TARGET MARKET CONSULTING AGREEMENT FOR REAL ESTATE PROPERTY MANAGEMENT SERVICES" / "TARGET MARKET CONSULTING AGREEMENT FOR REAL ESTATE PROPERTY MANAGEMENT SERVICES"
A49: 48 | B49: open | C49: [Chicago · DEPARTMENT OF FLEET AND FACILITY MANAGEMENT] SPECIFICATION: 1200982 PARTS AND SERVICES FOR: GROUP C: CUMMINS ENGINES | D49: Chicago fleet department buying engine parts and repair services; no information-handling problem stated. | E49: G1 current, G2 need, G3 not trivial | F49: "PARTS AND SERVICES FOR: GROUP C: CUMMINS ENGINES" / "PARTS AND SERVICES FOR: GROUP C: CUMMINS ENGINES" / "PARTS AND SERVICES FOR: GROUP C: CUMMINS ENGINES" | G49: commodity
A50: 49 | B50: open | C50: [Chicago · DEPARTMENT OF FLEET AND FACILITY MANAGEMENT] NON-TARGET MARKET MASTER CONSULTING AGREEMENT FOR REAL ESTATE PROPERTY MANAGEMENT SERVICES | D50: City fleet and facility department needs real estate property management consulting; no specific operational problem stated. | E50: G1 current, G2 need | F50: "NON-TARGET MARKET MASTER CONSULTING AGREEMENT FOR REAL ESTATE PROPERTY MANAGEMENT SERVICES" / "NON-TARGET MARKET MASTER CONSULTING AGREEMENT FOR REAL ESTATE PROPERTY MANAGEMENT SERVICES"
A51: 50 | B51: open | C51: [Chicago · DEPARTMENT OF FLEET AND FACILITY MANAGEMENT] MAINTENANCE, REPAIR AND PARTS ON PRESSROOM, BINDERY, PHOTOGRAPHIC EQUIPMENT AND LARGE FORMAT | D51: City print shop staff needing physical repair and maintenance of printing equipment. | E51: G1 current | F51: "MAINTENANCE, REPAIR AND PARTS ON PRESSROOM, BINDERY, PHOTOGRAPHIC EQUIPMENT AND LARGE FORMAT PRINTERS (GROUPS A & B)"
A52: 51 | B52: open | C52: [Chicago · DEPARTMENT OF PLANNING AND DEVELOPMENT] NON-TARGET MARKET PLANNING NOW SERVICES- CATEGORY 2: EVALUATE REAL ESTATE HOUSING & | D52: Chicago planning staff needing consultants to evaluate development proposals and support TIF district administration. | E52: G1 current | F52: "EVALUATE REAL ESTATE HOUSING & ECONOMIC DEVELOPMENT PROPOSALS & STUDY ECONOMIC IMPACTS;"
A53: 52 | B53: open | C53: [Chicago · DEPARTMENT OF FLEET AND FACILITY MANAGEMENT] PROPERTY MANAGEMENT SERVICES FOR THE HAROLD WASHINGTON LIBRARY CENTER | D53: City fleet and facility department managing a large library building. | E53: G1 current, G2 need | F53: "PROPERTY MANAGEMENT SERVICES FOR THE HAROLD WASHINGTON LIBRARY CENTER','','' ,'']" / "PROPERTY MANAGEMENT SERVICES FOR THE HAROLD WASHINGTON LIBRARY CENTER"
A54: 53 | B54: open | C54: [Chicago · CHICAGO FIRE DEPARTMENT] LAERDAL ADVANCED PATIENT SIMULATORS, PARTS, SUPPLIES, ACCESSORIES AND SERVICES | D54: Fire department buys patient simulator equipment and parts for training. | E54: G1 current, G2 need, G3 not trivial | F54: "LAERDAL ADVANCED PATIENT SIMULATORS, PARTS, SUPPLIES, ACCESSORIES AND SERVICES" / "LAERDAL ADVANCED PATIENT SIMULATORS, PARTS, SUPPLIES, ACCESSORIES AND SERVICES" / "LAERDAL ADVANCED PATIENT SIMULATORS, PARTS, SUPPLIES, ACCESSORIES AND SERVICES" | G54: commodity
A55: 54 | B55: open | C55: [Chicago · CHICAGO DEPARTMENT OF AVIATION] AIRSIDE CONCRETE PAVEMENT AND RAMP REPLACEMENT AND CONCRETE CRUSHING O�HARE AND MIDWAY | D55: Aviation department needs airfield concrete pavement replaced; physical construction work, not an information problem. | E55: G1 current | F55: "AIRSIDE CONCRETE PAVEMENT AND RAMP REPLACEMENT AND CONCRETE CRUSHING O�HARE AND MIDWAY INTERNATIONAL AIRPORTS"
A56: 55 | B56: open | C56: [Chicago · CHICAGO DEPARTMENT OF AVIATION] (Spec 1318223) Operation and Maintenance of the Airport Transit System (ATS) at | D56: Aviation department needs physical operation and maintenance of the airport train system. | E56: G1 current | F56: "Operation and Maintenance of the Airport Transit System (ATS) at Chicago O'Hare International Airport"
A57: 56 | B57: open | C57: [Chicago · CHICAGO FIRE DEPARTMENT] MSA SELF CONTAINED BREATHING APPARATUS (SCBA), HONEYWELL POSICHEK AND OCCUPATIONAL HEALTH DYNAMICS | D57: Fire department needs maintenance and repair of breathing apparatus and fit-testing equipment. | E57: G1 current | F57: "SELF CONTAINED BREATHING APPARATUS (SCBA), HONEYWELL POSICHEK AND OCCUPATIONAL HEALTH DYNAMICS (OHD) QUANTIFIT SYSTEM EQUIPMENT MAINTENANCE, REPAIR, PARTS AND SUPPLIES"
A58: 57 | B58: open | C58: [Chicago · DEPARTMENT OF WATER MANAGEMENT] 373766: BIRD DETERRENT MAINTENANCE AND SERVICES | D58: Water department needs physical bird deterrent maintenance at facilities; not an information-handling problem. | E58: G2 need | F58: "BIRD DETERRENT MAINTENANCE AND SERVICES"
A59: 58 | B59: open | C59: [Chicago · DEPARTMENT OF FLEET AND FACILITY MANAGEMENT] (Spec 81885) MAINTENANCE, REPAIR, TESTING AND PURCHASE OF AUDIO VISUAL SYSTEMS AND | D59: Facilities department needs AV system maintenance, repair, and equipment purchases; physical work, not information handling. | E59: G1 current | F59: "MAINTENANCE, REPAIR, TESTING AND PURCHASE OF AUDIO VISUAL SYSTEMS AND COMPONENTS"
A60: 59 | B60: open | C60: [New York City · Youth and Community Development] Technical Assistance Services for Case Management. In the areas of Organization Development, | D60: City youth agency needs capacity-building help for contracted providers doing case management. | E60: G4 author has it | F60: "to support our contracted providers and the work they do for the City of New York."
A61: 60 | B61: open | C61: [New York City · Youth and Community Development] Security System equipment and installation for DYCD offices. The Mayors Office of | D61: DYCD needs physical security hardware installed in newly renovated office space. | E61: G3 not trivial | F61: "Security System equipment and installation for DYCD offices." | G61: commodity
A62: 61 | B62: open | C62: [New York City · Emergency Management] Audio-Visual Software and Equipment Maintenance Renewal #2 | D62: Emergency Management maintains audio-visual software and equipment under a renewed maintenance contract. | E62: G3 not trivial | F62: "Audio-Visual Software and Equipment Maintenance Renewal #2" | G62: commodity
A63: 62 | B63: open | C63: [New York City · Citywide Administrative Services] Elevator Drive Repairs. Furnish all labor, materials, tools, and equipment necessary to | D63: City facility managers need elevator drive equipment repaired or replaced. | E63: G1 current | F63: "Furnish all labor, materials, tools, and equipment necessary to repair or replace elevator drives. Category: Services (other than human services)"
A64: 63 | B64: open | C64: [New York City · Environmental Protection] BWS Water Utility Climate Alliance Membership 7010186X | D64: None stated; this is an organizational membership fee with no operational process described. | E64: G1 current, G2 need, G4 author has it | F64: "BWS Water Utility Climate Alliance Membership 7010186X Category: Services (other than human services), Other." / "BWS Water Utility Climate Alliance Membership 7010186X" / "BWS Water Utility Climate Alliance Membership 7010186X"
A65: 64 | B65: open | C65: [New York City · Environmental Protection] BWS-DEL-462: Feasibility Study of Enlarging the Cannonsville Dam to Increase reservoir capacity | D65: NYC water agency needs an engineering feasibility study for expanding a reservoir dam. | E65: G1 current, G4 author has it | F65: "Feasibility Study of Enlarging the Cannonsville Dam to Increase reservoir capacity" / "Category: Services (other than human services), Government to Government."
A66: 65 | B66: open | C66: [New York City · Consumer and Worker Protection] Continuation of subscription support and maintenance services. Continuation of subscription support and | D66: Unclear; consumer protection department renewing an unnamed software subscription with no stated purpose. | E66: G2 need, G3 not trivial | F66: "Continuation of subscription support and maintenance services" / "Continuation of subscription support and maintenance services" | G66: unnamed subscription
A67: 66 | B67: open | C67: [New York City · Environmental Protection] NYS OGS BWSO Rental of box trucks 6001234X/7001214X | D67: City environmental department renting box trucks; vehicle rental, not an information-handling problem. | E67: G1 current, G2 need, G3 not trivial | F67: "NYS OGS BWSO Rental of box trucks 6001234X/7001214X','','',''" / "NYS OGS BWSO Rental of box trucks 6001234X/7001214X" / "NYS OGS BWSO Rental of box trucks 6001234X/7001214X" | G67: commodity
A68: 67 | B68: open | C68: [New York City · Fire Department] WTC Data Center and Clinical Center of Excellence. The Fire Department responded | D68: FDNY WTC health program staff coordinating federally funded health care data and clinical services. | E68: G4 author has it | F68: "responded to a Request for Proposal from the United States Department of Health and Human Services,"
A69: 68 | B69: open | C69: [New York City · Information Technology and Telecommunications] Citywide Voice and Data (TWC/Spectrum) Renewal 2 | D69: NYC DoITT renewing telecom carrier service for citywide voice and data connectivity. | E69: G1 current, G2 need, G3 not trivial | F69: "Citywide Voice and Data (TWC/Spectrum) Renewal 2 Category: Services (other than human services), Renewal." / "Citywide Voice and Data (TWC/Spectrum) Renewal 2" / "Citywide Voice and Data (TWC/Spectrum) Renewal 2" | G69: TWC/Spectrum
A70: 69 | B70: open | C70: [New York City · Sanitation] ImageWork ClaimConnect License Renewal and Support | D70: Sanitation department staff managing claims need ongoing license and support for claims software. | E70: G2 need, G3 not trivial | F70: "ImageWork ClaimConnect License Renewal and Support" / "ImageWork ClaimConnect License Renewal and Support" | G70: ImageWork ClaimConnect
A71: 70 | B71: open | C71: [New York City · Dept. of Social Svcs/Human Resources Administration] ITS Hardware-ServiceNow. DSS/ITS is requesting the following:1) REQ0236489/REQ0230541/SO0001216: DHS/ITS is requesting the | D71: City IT staff buying standard laptops and meeting hardware for agency offices. | E71: G2 need | F71: "This purchase is for the Commissioner's office new hires/senior staff."
A72: 71 | B72: open | C72: [New York City · Housing Preservation and Development] NAHRO Subscription. NAHRO shall provide HPD with the full range of services | D72: HPD staff buying a professional association membership for training and publications; no operational process problem. | E72: G1 current, G2 need, G3 not trivial | F72: "access to members only free webinars on the latest housing and community development topics, subscriptions to members only updates, emails and publications," / "NAHRO shall provide HPD with the full range of services available to its member organizations," / "NAHRO Subscription. NAHRO shall provide HPD with the full range of services" | G72: NAHRO membership
A73: 72 | B73: open | C73: [New York City · Environmental Protection] FMC Air Monitoring 6200041X / 7200036X | D73: NYC environmental protection staff running air monitoring with unclear data and reporting needs. | E73: G2 need | F73: "FMC Air Monitoring 6200041X / 7200036X"
A74: 73 | B74: open | C74: [New York City · Small Business Services] The Consultant will be responsible for planning, managing, and delivering FastTrac® NewVenture | D74: NYC Small Business Services needs entrepreneurship bootcamps delivered for aspiring business owners. | E74: G1 current | F74: "a series of free multiple-session entrepreneurship bootcamps for entrepreneurs planning to launch a business in New York City."}]}]"
A75: 74 | B75: open | C75: [New York City · Citywide Administrative Services] 102(f) Prof Dev Training MRW Consulting Group. Professional Development Off-the-Shelf Training | D75: No operational problem stated; generic off-the-shelf staff training purchase. | E75: G2 need, G3 not trivial, G4 author has it | F75: "102(f) Prof Dev Training MRW Consulting Group. Professional Development Off-the-Shelf Training" / "Professional Development Off-the-Shelf Training" / "102(f) Prof Dev Training MRW Consulting Group. Professional Development Off-the-Shelf Training" | G75: commodity
A76: 75 | B76: open | C76: [New York City · Sanitation] Pneumatic Tire Casing Retreading and Repair Services | D76: Sanitation department fleet managers needing tire retreading and repair for vehicles. | E76: G1 current, G3 not trivial | F76: "Pneumatic Tire Casing Retreading and Repair Services Category: Services (other than human services), Competitive Sealed Bids. Amount: $4,500,000. Date: 2026-09-23." / "Pneumatic Tire Casing Retreading and Repair Services" | G76: commodity
A77: 76 | B77: open | C77: [New York City · Environmental Protection] 82626Y0860-BWT Inspection, Testing & Repair of fire extinguishers & breathing apparatus 7030002X | D77: Environmental Protection staff needing safety equipment inspected, tested, and repaired on schedule. | E77: G1 current | F77: "Inspection, Testing & Repair of fire extinguishers & breathing apparatus 7030002X"
A78: 77 | B78: open | C78: [New York City · Environmental Protection] CRO-658: Halogen Eclipse Actuator Service and Equipment Purchase at Multiple DEP Facilities | D78: DEP facilities needing actuator equipment service; no information-handling problem stated. | E78: G1 current, G2 need, G3 not trivial | F78: "Halogen Eclipse Actuator Service and Equipment Purchase at Multiple DEP Facilities" / "Halogen Eclipse Actuator Service and Equipment Purchase at Multiple DEP Facilities" / "Halogen Eclipse Actuator Service and Equipment Purchase at Multiple DEP Facilities" | G78: commodity
A79: 78 | B79: open | C79: [New York City · Administration for Children's Services] Open Text ECM Support and Other Records Management Support | D79: ACS staff needing support for their enterprise content and records management system. | E79: G3 not trivial | F79: "Open Text ECM Support and Other Records Management Support" | G79: Open Text ECM
A80: 79 | B80: open | C80: [New York City · Youth and Community Development] The New York City Department of Youth and Community Development (DYCD) funds | D80: DYCD needs a vendor to supply meals for its child and adult food program sites. | E80: G3 not trivial | F80: "providing safe, consistent, and reliable supply of nutritious, healthy and culturally appropriate unitized meals" | G80: commodity
A81: 80 | B81: open | C81: [New York City · Health and Mental Hygiene] FY27-RQS/New Contract/Advocacy Services. The New York State Office of Mental Health ('OMH') | D81: State-mandated training contract for perinatal and early childhood mental health; no city software workflow problem. | E81: G1 current, G4 author has it | F81: "to operate the Citywide Perinatal and Early Childhood Mental Health Training and Technical Assistance Center (TTAC)" / "requires the NYC Department of Health and Mental Hygiene to contract with The New York Center for Child Development"
A82: 81 | B82: open | C82: [New York City · Parks and Recreation] NYC Parks Certified Playground Safety Inspector Certification (CPSI) Training in Flushing, NY | D82: NYC Parks needs inspectors trained and certified in playground safety. | E82: G1 current | F82: "NYC Parks Certified Playground Safety Inspector Certification (CPSI) Training in Flushing, NY"
A83: 82 | B83: open | C83: [New York City · Citywide Administrative Services] FY27 American Public Training LLC dba Graduate School USA Audit training and | D83: City staff need audit and grants management training; no operational software problem stated. | E83: G2 need, G3 not trivial, G4 author has it | F83: "FY27 American Public Training LLC dba Graduate School USA Audit training and Grants Management Trainings" / "FY27 American Public Training LLC dba Graduate School USA Audit training and Grants Management Trainings" / "FY27 American Public Training LLC dba Graduate School USA Audit training and Grants Management Trainings" | G83: commodity
A84: 83 | B84: open | C84: [New York City · Information Technology and Telecommunications] NYFA - Grant Program Administration (MOME). NYFA contract to develop, administer, and | D84: City media office funds grants for women-led media content via an outside arts nonprofit. | E84: G4 author has it | F84: "encourage and support the creation of film, television, digital, theatrical, and other forms of media and entertainment in NYC"
A85: 84 | B85: open | C85: [New York City · Citywide Administrative Services] Annual subscription and support renewal for IBM SPSS | D85: City analysts need continued access to statistical analysis software. | E85: G2 need, G3 not trivial | F85: "Annual subscription and support renewal for IBM SPSS" / "Annual subscription and support renewal for IBM SPSS" | G85: IBM SPSS
A86: 85 | B86: open | C86: [New York City · Sanitation] EH Fire Suppression Renewal 1. Maintenance, Inspection, and Repair Services for the | D86: Sanitation department needs upkeep and inspection of fire suppression and eyewash equipment at transfer stations. | E86: G1 current | F86: "Maintenance, Inspection, and Repair Services for the Fire Protection Systems & Emergency Eye Wash & Showers at DSNY Marine Transfer Stations"
A87: 86 | B87: open | C87: [New York City · Small Business Services] Challenged Based Procurement - Venture Forward. Although street vending provides critical services | D87: Street vendors struggle to navigate regulations and find legal vending opportunities in NYC. | E87: G4 author has it | F87: "we are endeavoring to support the economic stability of street vendors who seek legal work"
A88: 87 | B88: open | C88: [New York City · Buildings] ELECTRICAL UNIT - SOLAR AND PY TRAINING | D88: Buildings electrical unit staff need solar and PV training; no software problem stated. | E88: G1 current, G2 need | F88: "ELECTRICAL UNIT - SOLAR AND PY TRAINING Category: Services (other than human services), Other.','','','','','','','','','','','','','','','','','','','','','','','','','','','','','','','','','','','','','','','','','','','','','','','','','','','','','','','','','','','','','','','','','','','','','','','','','','','','','','','','','','','','','','','','','','','','','','','','','','','','','','','','','','','','','','','','','','','','','','','','','','','','','','','','','','','','','','','','','','','','','','','','','','','','','','','','','','','','','','','','','','','','','','','','','','','','','','','','','','','','','','','','','','','','','','','" / "ELECTRICAL UNIT - SOLAR AND PY TRAINING"
A89: 88 | B89: open | C89: Tell HN: AI coding is sexy, but accounting is the real low-hanging target | D89: Founder opines that small-business bookkeeping is easily automatable; no specific problem or request. | E89: G3 not trivial | F89: "most of the work feels like: normalize data from banks / cards / invoices apply deterministic or configurable rules surface exceptions" | G89: QuickBooks
A90: 89 | B90: open | C90: How are you LLM-coding in an established code base? | D90: Startup engineers lack a service to spin up full multi-service stacks for LLM-written code verification. | E90: G2 need | F90: "AFAICT, there's no service that lets me: give a prompt, write the code, spin up all this infra, run Playwright,"
A91: 90 | B91: open | C91: What are your AI assistants doing? | D91: Hobbyist asks others how they use AI agents; no concrete unsolved problem stated. | E91: G1 current, G2 need, G3 not trivial, G4 author has it | F91: "I automate the tedious and try to find little things to do, but I could do these things by hand if I really wanted." / "So my question is, what do you use agents like this for? Is it strictly for fun or also for profit?" / "I make small automations, 1 of them does not even need an LLM, only the profile matching does." / "It's fun, certainly, the LLM assumes the ST Voyager computer persona, answers with Vulcan salutes" | G91: OpenClaw
A92: 91 | B92: open | C92: 5 App ideas people are asking for on Reddit right now | D92: Author promoting a pain-point catalog tool; no personal problem of their own. | E92: G2 need, G4 author has it | F92: "What would you build from this list? Anyone working on something similar?" / "it scans Reddit for validated pain points organized by niche. Happy to share more for any specific niche if anyone's curious."
A93: 92 | B93: open | C93: Dumping GitHub for Forgejo for a free and open source project | D93: Open source maintainer wants Forgejo hosting without losing GitHub contributors' issues and PRs. | E93: G3 not trivial | F93: "I keep a mirror on github, utilize issues and PRs there." | G93: Forgejo/GitHub mirroring
A94: 93 | B94: open | C94: Built an AI-powered profit calculator and inventory tracker app for resellers | D94: Resellers researching item profitability and tracking inventory; post is a developer promoting his own app. | E94: G1 current, G2 need, G3 not trivial, G4 author has it | F94: "Launched 2 months ago 10 free analyses to start Paid tiers from $2.99/mo Active users in flipping community" / "How would you improve the AI prompts for better accuracy? What's a fair price for this kind of analysis tool?" / "So I built Underpriced.app - an AI reseller app that tells you if something is worth flipping before you buy it." / "Promoting SaaS is way harder than building it The reselling community is way bigger than I expected" | G94: Underpriced.app
A95: 94 | B95: open | C95: Hit Supabase's free→$25 pricing cliff. Any middle-tier options? | D95: Solo builder hit Supabase free-tier egress cap; wants a cheaper middle pricing tier. | E95: G3 not trivial | F95: "Upgrade to Pro at $25/mo, instantly unblocked" | G95: Supabase Pro
A96: 95 | B96: open | C96: I have an interesting idea to reduce the output tokens almost by fifty percent | D96: AI coding agent users wasting output tokens restating old code during edits. | E96: G2 need | F96: "I hope any harness builder who sees this post will apply it to a harness."
A97: 96 | B97: open | C97: My family business runs on a 1993-era text-based-UI (TUI). Anybody else? | D97: Family wholesale distributor on a legacy 1993 TUI system with brittle automation scripts. | E97: G1 current, G2 need | F97: "I'm not sure if I'm blinded by nostalgia or if this application is truly as wonderful as I remember it." " / "I’d love to hear if and how these are still being utilized in the real world."
A98: 97 | B98: open | C98: Invoice OCR API for Logistics Expense Tracking Automation | D98: Logistics companies manually entering invoice data; post reads as OCR API promotion. | E98: G1 current, G2 need, G3 not trivial, G4 author has it | F98: "Manually recording these expenses can slow down financial tracking and increase the chances of data entry errors." / "An Invoice OCR API helps automate this process by extracting important information directly from invoice images or PDFs." / "An Invoice OCR API helps automate this process by extracting important information directly from invoice images or PDFs." / "Logistics and transportation companies handle large volumes of invoices for fuel, freight, tolls, and vendor services." | G98: Invoice OCR API
A99: 98 | B99: open | C99: AI Aadhaar OCR API for Fast Aadhaar Data Extraction | D99: Fintech and KYC businesses needing Aadhaar card data extraction (post is a product promotion). | E99: G3 not trivial | F99: "We built an AI-powered Aadhaar OCR API that can extract data from Aadhaar cards instantly for KYC automation." | G99: Aadhaar OCR API
A100: 99 | B100: open | C100: Sentient: Transform Customer Feedback into Actionable Intelligence with AI | D100: Founder promoting an AI feedback analysis product; no problem stated. | E100: G1 current, G2 need, G3 not trivial, G4 author has it | F100: "We're excited to share Sentient, an AI-powered customer intelligence platform that transforms raw customer feedback into actionable business insights in under 60 seconds." / "Try It Now: - Live Demo - https://usesentient.app/demo - Pricing - https://usesentient.app/pri" / "Sentient uses advanced neural networks to analyze customer feedback and extract: - Sentiment Analysis" / "Hi HN! We're excited to share Sentient, an AI-powered customer intelligence platform that transforms raw customer feedback" | G100: an LLM
...

Sheet Summary
A1: Phase 0 summary
A2: Inputs (fill in)
A3: Manual search minutes before abandoning | C3: From your timer: start 10:39 PM on 2026-10-03 to when you stopped. Enter minutes.
A4: Minutes spent reviewing this workbook | C4: Start a timer when you open this file; enter minutes when done.
A5: Results (formulas)
A6: Candidates | B6: =COUNTA(Candidates!$C$5:$C$39) | C6: Rows on the Candidates sheet.
A7: Labeled | B7: =COUNTIF(Candidates!$N$5:$N$39,"yes")+COUNTIF(Candidates!$N$5:$N$39,"maybe")+COUNTIF(Candidates!$N$5:$N$39,"no") | C7: Rows with Pursue? filled in.
A8: Pursue = yes | B8: =COUNTIF(Candidates!$N$5:$N$39,"yes")
A9: Pursue = maybe | B9: =COUNTIF(Candidates!$N$5:$N$39,"maybe")
A10: Pursue = no | B10: =COUNTIF(Candidates!$N$5:$N$39,"no")
A11: Precision of top 20 (yes ÷ candidates) | B11: =IF(B6=0,0,B8/B6) | C11: REQUIREMENTS §9: share of the top 20 you label interesting.
A12: Precision, lenient (yes + maybe ÷ candidates) | B12: =IF(B6=0,0,(B8+B9)/B6)
A13: Top 10 by scout ranking: share yes | B13: =COUNTIFS(Candidates!$A$5:$A$39,"<=10",Candidates!$N$5:$N$39,"yes")/10 | C13: Hybrid ranking (rows 1–10 as delivered).
A14: Top 10 by rules-only ranking: share yes | B14: =COUNTIFS(Candidates!$S$5:$S$39,"<=10",Candidates!$N$5:$N$39,"yes")/10 | C14: Same rows ranked by rules only. Higher than the line above means the model didn't help.
A15: Shortlist after your edits | B15: =COUNTIF(Candidates!$M$5:$M$39,"Shortlist") | C15: Band = Shortlist. Scorer v2 rows: all gates pass, no unsupported score. Older rows: Total ≥ 15.
A16: Scores you changed | B16: =SUM(Candidates!$P$5:$P$39) | C16: FR-18: overrides are labels for measuring scoring quality.
A17: Hours per qualified opportunity (assisted) | B17: =IF(B8=0,0,B4/60/B8) | C17: Review minutes ÷ 60 ÷ yes count. 0 until you enter minutes and label.
A18: Run info
A19: Generated | B19: 2026-10-05T13:39:07.013Z
A20: Scoring method | B20: Scorer v2 (ADR-003): gates G1–G4, then Pain, Messy, Backend, Reachable, Buyer for HN by claude-sonnet-5-5 (prompt judge-v2.1) on the top 270 HN items by rule score, each with a quote checked against the post. HN total excludes Frequency (shown as popularity) and unsupported scores. USAspending: rules.

Sheet Rubric
A1: Criterion | B1: 1 | C1: 2 | D1: 3 | E1: Scored by
A2: Frequency | B2: Seen once | C2: 2–3 times, or in 2 places | D2: Recurring across sources or many comments | E2: Rule. Scorer v2: HN shows comment count as popularity, not in the total
A3: Pain | B3: Annoyance, no cost stated | C3: Time or money cost implied | D3: Hours or dollars stated | E3: Model (HN), rule (USAspending)
A4: Messy data | B4: One clean source | C4: Some variants or missing fields | D4: Several sources, no shared key | E4: Model (HN), rule (USAspending)
A5: Backend weight | B5: Mostly UI / forms | C5: Some ingestion or matching | D5: Real ingestion, matching, storage | E5: Model (HN), rule (USAspending)
A6: Reachable | B6: Can't say where they gather | C6: A broad community | D6: A specific place to message 5 of them | E6: Model (HN), rule (USAspending)
A7: Buyer (v2) | B7: Frustrated user, no budget | C7: Freelancer or small team that pays for tools | D7: Business or department already spending on it | E7: Model (HN only)
A8: Free data | B8: Needs paid/private data | C8: Partly public | D8: Prototype fully on public data | E8: Rule
A9: Total | B9: 6–18 | C9: ≥ 15 = Shortlist | D9: < 10 = Drop | E9: v2 HN: Pain+Messy+Backend+Reach+Buyer+Free data, supported scores only
A10: Gates (v2) | B10: G1 current problem · G2 asks for help / written need | C10: G3 not solvable with an existing tool | D10: G4 author has the problem (not selling) | E10: Model; a failed gate moves the post to the Gated out sheet
A12: Higher is better: 3 is the strongest score on every criterion, 1 the weakest.
